{
  "chapter": 21,
  "layer": "hebrewpara",
  "verses": {
    "신명기 21:1": {
      "type": "text",
      "content": "“네 하나님 여호와께서 네게 차지하라고 주신 땅에서, 만일 들에 쓰러진 시체가 발견되었는데 누가 그를 쳐 죽였는지 알 수 없거든,"
    },
    "신명기 21:2": {
      "type": "text",
      "content": "너의 장로들과 재판관들이 나가서, 그 시체에서부터 주변에 있는 성읍들까지의 거리를 재어라."
    },
    "신명기 21:3": {
      "type": "text",
      "content": "그리고 그 시체에서 가장 가까운 성읍의 장로들은, 아직 일을 시키지 아니하였고 멍에를 메지 아니한 암송아지 한 마리를 데려다가,"
    },
    "신명기 21:4": {
      "type": "text",
      "content": "그 성읍의 장로들이 항상 물이 흐르고 갈지도 심지도 못한 골짜기로 그 송아지를 끌고 가서, 그 골짜기에서 그 송아지의 목을 꺾어라."
    },
    "신명기 21:5": {
      "type": "text",
      "content": "그때에 레위 자손 제사장들도 그곳으로 나아와야 한다. 그들은 네 하나님 여호와께서 자기를 섬기게 하시며 또 여호와의 이름으로 축복하게 하시려고 택하신 자들이며, 모든 소송과 모든 폭행 사건이 그들의 말에 따라 결정된다."
    },
    "신명기 21:6": {
      "type": "text",
      "content": "그 시체에서 가장 가까운 성읍의 모든 장로는 그 골짜기에서 목이 꺾인 그 암송아지 위에 손을 씻으며,"
    },
    "신명기 21:7": {
      "type": "text",
      "content": "이렇게 증언하여라. ‘우리의 손이 이 피를 흘리지 아니하였고, 우리 눈도 이 일을 보지 아니하였습니다."
    },
    "신명기 21:8": {
      "type": "text",
      "content": "여호와여, 주께서 속량하신 주의 백성 이스라엘을 용서하시고, 무죄한 피의 책임을 주의 백성 이스라엘 가운데 두지 마옵소서.’ 그리하면 그 피흘림의 죄가 그들에게 속하여질 것이다."
    },
    "신명기 21:9": {
      "type": "text",
      "content": "너는 이같이 하여, 너희 가운데서 무죄한 피흘림의 죄를 제거하여라. 그것이 여호와의 눈에 옳은 일을 행하는 것이다.”"
    },
    "신명기 21:10": {
      "type": "text",
      "content": "“네가 원수와 싸우러 나갔을 때에 네 하나님 여호와께서 그들을 네 손에 넘기셔서 네가 그들을 사로잡은 후에,"
    },
    "신명기 21:11": {
      "type": "text",
      "content": "그 포로 가운데서 아름다운 여자를 보고 마음에 끌려 아내로 삼고자 하거든,"
    },
    "신명기 21:12": {
      "type": "text",
      "content": "너는 그 여자를 네 집으로 데려가고, 그 여자는 자기 머리를 밀고 손톱을 깎으며,"
    },
    "신명기 21:13": {
      "type": "text",
      "content": "포로 시절의 옷을 벗고 네 집에 살면서 한 달 동안 자기 부모를 위하여 애곡한 후에, 너는 그 여자에게로 들어가서 그의 남편이 되고 그 여자는 네 아내가 될 것이다."
    },
    "신명기 21:14": {
      "type": "text",
      "content": "그 후에 만일 네가 그 여자를 좋아하지 아니하면, 그 여자가 원하는 곳으로 가게 하여라. 결코 돈을 받고 팔지 말고 종으로 다루지 말아라. 이는 네가 그 여자를 욕보였기 때문이다.”"
    },
    "신명기 21:15": {
      "type": "text",
      "content": "“어떤 사람에게 두 아내가 있어서, 하나는 사랑을 받고 하나는 미움을 받는데 사랑받는 자와 미움받는 자가 모두 아들을 낳았고, 미움받는 자의 아들이 장자라면,"
    },
    "신명기 21:16": {
      "type": "text",
      "content": "그가 자기 재산을 그 아들들에게 기업으로 나누어 주는 날에, 사랑받는 자의 아들을 미움받는 자의 아들인 참 장자보다 앞세워 장자로 삼지 못한다."
    },
    "신명기 21:17": {
      "type": "text",
      "content": "도리어 그는 그 미움받는 자의 아들을 장자로 인정하여 자기 모든 소유에서 그에게 두 몫을 주어야 한다. 그는 그의 기력의 시작이니, 장자의 권리가 그에게 있기 때문이다.”"
    },
    "신명기 21:18": {
      "type": "text",
      "content": "“어떤 사람에게 완고하고 반항하는 아들이 있어서, 자기 아비의 말과 어미의 말을 듣지 아니하고, 부모가 매를 들어 훈계해도 듣지 않거든,"
    },
    "신명기 21:19": {
      "type": "text",
      "content": "그 부모는 그를 잡아 그 성문 곧 그 성읍의 장로들에게 데리고 나가서,"
    },
    "신명기 21:20": {
      "type": "text",
      "content": "그 성읍의 장로들에게 말하여라. ‘우리의 이 아들은 완고하고 반항적이며 우리 말을 듣지 아니하고 방탕하며 술에 빠진 자입니다.’"
    },
    "신명기 21:21": {
      "type": "text",
      "content": "그러면 그 성읍의 모든 사람이 그를 돌로 쳐 죽일 것이다. 너는 이같이 하여 너희 가운데서 악을 제거하여라. 그리하면 온 이스라엘이 듣고 두려워할 것이다.”"
    },
    "신명기 21:22": {
      "type": "text",
      "content": "“어떤 사람이 죽을 죄를 지어 사형에 처해지고 너희가 그를 나무에 매달았거든,"
    },
    "신명기 21:23": {
      "type": "text",
      "content": "그의 시체를 나무 위에 밤새도록 두지 말고, 반드시 당일에 묻어라. 나무에 매달린 자는 하나님께 저주받은 자이니, 네 하나님 여호와께서 네게 기업으로 주시는 땅을 너는 더럽히지 말아라.”"
    }
  }
}
