{"chapter":18,"layer":"hebrew","verses":{"여호수아 18:1":{"type":"wordblock","text":"וַ/יִּקָּ֨הֲל֜וּ כָּל עֲדַ֤ת בְּנֵֽי יִשְׂרָאֵל֙ שִׁלֹ֔ה וַ/יַּשְׁכִּ֥ינוּ שָׁ֖ם אֶת אֹ֣הֶל מוֹעֵ֑ד וְ/הָ/אָ֥רֶץ נִכְבְּשָׁ֖ה לִ/פְנֵי/הֶֽם","words":[{"word":"וַ/יִּקָּ֨הֲל֜וּ","pron":"바이카하루","meaning":"모이다","lemma":"קָהַל","morph":"Niphal 연속미완료 3인칭 남성 복수","pos":"동사","meanings":["회집하다"],"note":"접속사 וְ → 그리고"},{"word":"כָּל","pron":"칼","meaning":"모든","lemma":"כֹּל","morph":"남성 단수","pos":"명사","meanings":["모든","전부"]},{"word":"עֲדַ֤ת","pron":"아닷","meaning":"회중","lemma":"עֵדָה","morph":"여성 단수","pos":"명사","meanings":["회중","무리"]},{"word":"בְּנֵֽי","pron":"브네","meaning":"아들","lemma":"בֵּן","morph":"남성 복수","pos":"명사","meanings":["아들","자손"]},{"word":"יִשְׂרָאֵל֙","pron":"이스라엘","meaning":"이스라엘","lemma":"יִשְׂרָאֵל","morph":"고유","pos":"명사","meanings":["이스라엘"],"nameType":"person"},{"word":"שִׁלֹ֔ה","pron":"시로","meaning":"실로","lemma":"שִׁילֹה","morph":"고유","pos":"명사","meanings":["실로"],"nameType":"place"},{"word":"וַ/יַּשְׁכִּ֥ינוּ","pron":"바앗키누","meaning":"거주하다","lemma":"שָׁכַן","morph":"Hiphil 연속미완료 3인칭 남성 복수","pos":"동사","meanings":["살다","장막을 치다"],"note":"접속사 וְ → 그리고"},{"word":"שָׁ֖ם","pron":"삼","meaning":"거기에","lemma":"שָׁם","morph":"","pos":"부사","meanings":["거기에","그곳에"]},{"word":"אֶת","pron":"엣","meaning":"(목적격)","lemma":"אֵת","morph":"직접목적격","pos":"소사","meanings":["직접 목적어 표지"]},{"word":"אֹ֣הֶל","pron":"오헬","meaning":"장막","lemma":"אֹהֶל","morph":"남성 단수","pos":"명사","meanings":["장막","천막"]},{"word":"מוֹעֵ֑ד","pron":"모엗","meaning":"정한 때","lemma":"מוֹעֵד","morph":"남성 단수","pos":"명사","meanings":["정한 때","절기"]},{"word":"וְ/הָ/אָ֥רֶץ","pron":"브하아렛","meaning":"땅","lemma":"אֶרֶץ","morph":"공성 단수","pos":"명사","meanings":["땅","토지","지역"],"note":"접속사 וְ → 그리고 / 정관사 הַ → 그"},{"word":"נִכְבְּשָׁ֖ה","pron":"닉브사","meaning":"정복하다","lemma":"כָּבַשׁ","morph":"Niphal 완료 3인칭 여성 단수","pos":"동사","meanings":["정복하다"]},{"word":"לִ/פְנֵי/הֶֽם","pron":"리프네헴","meaning":"얼굴","lemma":"פָּנִים","morph":"공성 복수","pos":"명사","meanings":["얼굴","앞"],"note":"전치사 לְ → ~에게/를 위해"}]},"여호수아 18:2":{"type":"wordblock","text":"וַ/יִּוָּֽתְרוּ֙ בִּ/בְנֵ֣י יִשְׂרָאֵ֔ל אֲשֶׁ֥ר לֹֽא חָלְק֖וּ אֶת נַֽחֲלָתָ֑/ם שִׁבְעָ֖ה שְׁבָטִֽים","words":[{"word":"וַ/יִּוָּֽתְרוּ֙","pron":"바이밧루","meaning":"남기다","lemma":"יָתַר","morph":"Niphal 연속미완료 3인칭 남성 복수","pos":"동사","meanings":["남기다","남다","넘치다"],"note":"접속사 וְ → 그리고"},{"word":"בִּ/בְנֵ֣י","pron":"비브네","meaning":"아들","lemma":"בֵּן","morph":"남성 복수","pos":"명사","meanings":["아들","자손"],"note":"전치사 בְּ → ~ 안에/으로"},{"word":"יִשְׂרָאֵ֔ל","pron":"이스라엘","meaning":"이스라엘","lemma":"יִשְׂרָאֵל","morph":"고유","pos":"명사","meanings":["이스라엘"],"nameType":"person"},{"word":"אֲשֶׁ֥ר","pron":"아셀","meaning":"~한 것","lemma":"אֲשֶׁר","morph":"관계","pos":"소사","meanings":["~인","~한 것"]},{"word":"לֹֽא","pron":"로","meaning":"아니","lemma":"לֹא","morph":"부정","pos":"소사","meanings":["아니","않다"]},{"word":"חָלְק֖וּ","pron":"할쿠","meaning":"나누다","lemma":"חָלַק","morph":"Qal 완료 3인칭 공성 복수","pos":"동사","meanings":["나누다","분배하다"]},{"word":"אֶת","pron":"엣","meaning":"(목적격)","lemma":"אֵת","morph":"직접목적격","pos":"소사","meanings":["직접 목적어 표지"]},{"word":"נַֽחֲלָתָ֑/ם","pron":"나하라타므","meaning":"기업","lemma":"נַחֲלָה","morph":"여성 단수","pos":"명사","meanings":["기업","유산","분깃"]},{"word":"שִׁבְעָ֖ה","pron":"십아","meaning":"일곱","lemma":"שֶׁבַע","morph":"기수 남성 단수","pos":"형용사","meanings":["일곱"]},{"word":"שְׁבָטִֽים","pron":"스바딤","meaning":"지팡이","lemma":"שֵׁבֶט","morph":"남성 복수","pos":"명사","meanings":["지팡이","지파"]}]},"여호수아 18:3":{"type":"wordblock","text":"וַ/יֹּ֥אמֶר יְהוֹשֻׁ֖עַ אֶל בְּנֵ֣י יִשְׂרָאֵ֑ל עַד אָ֨נָה֙ אַתֶּ֣ם מִתְרַפִּ֔ים לָ/בוֹא֙ לָ/רֶ֣שֶׁת אֶת הָ/אָ֔רֶץ אֲשֶׁר֙ נָתַ֣ן לָ/כֶ֔ם יְהוָ֖ה אֱלֹהֵ֥י אֲבֽוֹתֵי/כֶֽם","words":[{"word":"וַ/יֹּ֥אמֶר","pron":"바오멜","meaning":"말하다","lemma":"אָמַר","morph":"Qal 연속미완료 3인칭 남성 단수","pos":"동사","meanings":["말하다","이르다"],"note":"접속사 וְ → 그리고"},{"word":"יְהוֹשֻׁ֖עַ","pron":"으호수아","meaning":"여호수아","lemma":"יְהוֹשׁוּעַ","morph":"고유","pos":"명사","meanings":["여호수아"],"nameType":"person"},{"word":"אֶל","pron":"엘","meaning":"~에게","lemma":"אֵל","morph":"","pos":"전치사","meanings":["~에게","~로"]},{"word":"בְּנֵ֣י","pron":"브네","meaning":"아들","lemma":"בֵּן","morph":"남성 복수","pos":"명사","meanings":["아들","자손"]},{"word":"יִשְׂרָאֵ֑ל","pron":"이스라엘","meaning":"이스라엘","lemma":"יִשְׂרָאֵל","morph":"고유","pos":"명사","meanings":["이스라엘"],"nameType":"person"},{"word":"עַד","pron":"앋","meaning":"~까지","lemma":"עַד","morph":"","pos":"전치사","meanings":["~까지"]},{"word":"אָ֨נָה֙","pron":"아나","meaning":"어디","lemma":"אָן","morph":"","pos":"부사","meanings":["어디","어디로"]},{"word":"אַתֶּ֣ם","pron":"아템","meaning":"너","lemma":"אַתָּה","morph":"인칭 2인칭 남성 복수","pos":"대명사","meanings":["너"]},{"word":"מִתְרַפִּ֔ים","pron":"밋라핌","meaning":"약해지다","lemma":"רָפָה","morph":"Hithpael 분사 능동 남성 복수","pos":"동사","meanings":["떨어뜨리다","약해지다"]},{"word":"לָ/בוֹא֙","pron":"라보","meaning":"오다","lemma":"בּוֹא","morph":"Qal 부정사 연계","pos":"동사","meanings":["오다","들어가다"],"note":"전치사 לְ → ~에게/를 위해"},{"word":"לָ/רֶ֣שֶׁת","pron":"라레셋","meaning":"차지하다","lemma":"יָרַשׁ","morph":"Qal 부정사 연계","pos":"동사","meanings":["소유하다","쫓아내다"],"note":"전치사 לְ → ~에게/를 위해"},{"word":"אֶת","pron":"엣","meaning":"(목적격)","lemma":"אֵת","morph":"직접목적격","pos":"소사","meanings":["직접 목적어 표지"]},{"word":"הָ/אָ֔רֶץ","pron":"하아렛","meaning":"땅","lemma":"אֶרֶץ","morph":"공성 단수","pos":"명사","meanings":["땅","토지","지역"],"note":"정관사 הַ → 그"},{"word":"אֲשֶׁר֙","pron":"아셀","meaning":"~한 것","lemma":"אֲשֶׁר","morph":"관계","pos":"소사","meanings":["~인","~한 것"]},{"word":"נָתַ֣ן","pron":"나탄","meaning":"주다","lemma":"נָתַן","morph":"Qal 완료 3인칭 남성 단수","pos":"동사","meanings":["주다","두다"]},{"word":"לָ/כֶ֔ם","pron":"라켐","meaning":"~에게/를 위해","lemma":"l","morph":"","pos":"접미대명사","meanings":["~에게/를 위해"],"note":"전치사 לְ"},{"word":"יְהוָ֖ה","pron":"여호와","meaning":"여호와","lemma":"יְהֹוָה","morph":"고유","pos":"명사","meanings":["여호와"],"nameType":"person"},{"word":"אֱלֹהֵ֥י","pron":"에로헤","meaning":"하나님","lemma":"אֱלֹהִים","morph":"남성 복수","pos":"명사","meanings":["하나님(엘로힘)","신들"]},{"word":"אֲבֽוֹתֵי/כֶֽם","pron":"아보테켐","meaning":"아버지","lemma":"אָב","morph":"남성 복수","pos":"명사","meanings":["아버지"]}]},"여호수아 18:4":{"type":"wordblock","text":"הָב֥וּ לָ/כֶ֛ם שְׁלֹשָׁ֥ה אֲנָשִׁ֖ים לַ/שָּׁ֑בֶט וְ/אֶשְׁלָחֵ֗/ם וְ/יָקֻ֜מוּ וְ/יִֽתְהַלְּכ֥וּ בָ/אָ֛רֶץ וְ/יִכְתְּב֥וּ אוֹתָ֛/הּ לְ/פִ֥י נַֽחֲלָתָ֖/ם וְ/יָבֹ֥אוּ אֵלָֽ/י","words":[{"word":"הָב֥וּ","pron":"하부","meaning":"주다","lemma":"יָהַב","morph":"Qal 권유형 2인칭 남성 복수","pos":"동사","meanings":["주다","두다","오라"]},{"word":"לָ/כֶ֛ם","pron":"라켐","meaning":"~에게/를 위해","lemma":"l","morph":"","pos":"접미대명사","meanings":["~에게/를 위해"],"note":"전치사 לְ"},{"word":"שְׁלֹשָׁ֥ה","pron":"스로사","meaning":"셋","lemma":"שָׁלוֹשׁ","morph":"기수 남성 단수","pos":"형용사","meanings":["셋"]},{"word":"אֲנָשִׁ֖ים","pron":"아나심","meaning":"사람","lemma":"אִישׁ","morph":"남성 복수","pos":"명사","meanings":["사람","남자"]},{"word":"לַ/שָּׁ֑בֶט","pron":"라사벧","meaning":"지팡이","lemma":"שֵׁבֶט","morph":"남성 단수","pos":"명사","meanings":["지팡이","지파"],"note":"전치사 לְ → ~에게/를 위해"},{"word":"וְ/אֶשְׁלָחֵ֗/ם","pron":"브엣라헤므","meaning":"보내다","lemma":"שָׁלַח","morph":"Qal 미완료 1인칭 공성 단수","pos":"동사","meanings":["보내다","내쫓다"],"note":"접속사 וְ → 그리고"},{"word":"וְ/יָקֻ֜מוּ","pron":"브아쿠무","meaning":"일어나다","lemma":"קוּם","morph":"Qal 미완료 3인칭 남성 복수","pos":"동사","meanings":["일어나다","세우다"],"note":"접속사 וְ → 그리고"},{"word":"וְ/יִֽתְהַלְּכ֥וּ","pron":"브잇할쿠","meaning":"가다","lemma":"הָלַךְ","morph":"Hithpael 미완료 3인칭 남성 복수","pos":"동사","meanings":["가다","걷다"],"note":"접속사 וְ → 그리고"},{"word":"בָ/אָ֛רֶץ","pron":"바아렛","meaning":"땅","lemma":"אֶרֶץ","morph":"공성 단수","pos":"명사","meanings":["땅","토지","지역"],"note":"전치사 בְּ → ~ 안에/으로"},{"word":"וְ/יִכְתְּב֥וּ","pron":"브익트부","meaning":"쓰다","lemma":"כָּתַב","morph":"Qal 미완료 3인칭 남성 복수","pos":"동사","meanings":["쓰다","기록하다"],"note":"접속사 וְ → 그리고"},{"word":"אוֹתָ֛/הּ","pron":"오타흐","meaning":"(목적격)","lemma":"אֵת","morph":"","pos":"접미대명사","meanings":["직접 목적어 표지"]},{"word":"לְ/פִ֥י","pron":"르피","meaning":"입","lemma":"פֶּה","morph":"남성 단수","pos":"명사","meanings":["입","명령"],"note":"전치사 לְ → ~에게/를 위해"},{"word":"נַֽחֲלָתָ֖/ם","pron":"나하라타므","meaning":"기업","lemma":"נַחֲלָה","morph":"여성 단수","pos":"명사","meanings":["기업","유산","분깃"]},{"word":"וְ/יָבֹ֥אוּ","pron":"브아보우","meaning":"오다","lemma":"בּוֹא","morph":"Qal 미완료 3인칭 남성 복수","pos":"동사","meanings":["오다","들어가다"],"note":"접속사 וְ → 그리고"},{"word":"אֵלָֽ/י","pron":"에라으","meaning":"~에게","lemma":"אֵל","morph":"","pos":"접미대명사","meanings":["~에게","~로"]}]},"여호수아 18:5":{"type":"wordblock","text":"וְ/הִֽתְחַלְּק֥וּ אֹתָ֖/הּ לְ/שִׁבְעָ֣ה חֲלָקִ֑ים יְהוּדָ֞ה יַעֲמֹ֤ד עַל גְּבוּל/וֹ֙ מִ/נֶּ֔גֶב וּ/בֵ֥ית יוֹסֵ֛ף יַעַמְד֥וּ עַל גְּבוּלָ֖/ם מִ/צָּפֽוֹן","words":[{"word":"וְ/הִֽתְחַלְּק֥וּ","pron":"브힛할쿠","meaning":"나누다","lemma":"חָלַק","morph":"Hithpael 연속완료 3인칭 공성 복수","pos":"동사","meanings":["나누다","분배하다"],"note":"접속사 וְ → 그리고"},{"word":"אֹתָ֖/הּ","pron":"오타흐","meaning":"(목적격)","lemma":"אֵת","morph":"","pos":"접미대명사","meanings":["직접 목적어 표지"]},{"word":"לְ/שִׁבְעָ֣ה","pron":"르십아","meaning":"일곱","lemma":"שֶׁבַע","morph":"","meanings":["일곱"],"note":"전치사 לְ → ~에게/를 위해"},{"word":"חֲלָקִ֑ים","pron":"하라킴","meaning":"분깃","lemma":"חֵלֶק","morph":"남성 복수","pos":"명사","meanings":["몫","분깃"]},{"word":"יְהוּדָ֞ה","pron":"으후다","meaning":"유다","lemma":"יְהוּדָה","morph":"고유","pos":"명사","meanings":["유다"],"nameType":"person"},{"word":"יַעֲמֹ֤ד","pron":"아아몯","meaning":"서다","lemma":"עָמַד","morph":"Qal 미완료 3인칭 남성 단수","pos":"동사","meanings":["서다"]},{"word":"עַל","pron":"알","meaning":"~위에","lemma":"עַל","morph":"","pos":"전치사","meanings":["위에","관하여"]},{"word":"גְּבוּל/וֹ֙","pron":"그불오","meaning":"경계","lemma":"גְּבוּל","morph":"남성 단수","pos":"명사","meanings":["경계","지경"]},{"word":"מִ/נֶּ֔גֶב","pron":"미네겝","meaning":"남방","lemma":"נֶגֶב","morph":"남성 단수","pos":"명사","meanings":["남방","네게브"],"note":"전치사 מִן → ~로부터"},{"word":"וּ/בֵ֥ית","pron":"우벳","meaning":"집","lemma":"בַּיִת","morph":"남성 단수","pos":"명사","meanings":["집","가문"],"note":"접속사 וְ → 그리고"},{"word":"יוֹסֵ֛ף","pron":"오셉","meaning":"요셉","lemma":"יוֹסֵף","morph":"고유","pos":"명사","meanings":["요셉"],"nameType":"person"},{"word":"יַעַמְד֥וּ","pron":"아암두","meaning":"서다","lemma":"עָמַד","morph":"Qal 미완료 3인칭 남성 복수","pos":"동사","meanings":["서다"]},{"word":"עַל","pron":"알","meaning":"~위에","lemma":"עַל","morph":"","pos":"전치사","meanings":["위에","관하여"]},{"word":"גְּבוּלָ֖/ם","pron":"그부라므","meaning":"경계","lemma":"גְּבוּל","morph":"남성 단수","pos":"명사","meanings":["경계","지경"]},{"word":"מִ/צָּפֽוֹן","pron":"미짜폰","meaning":"북쪽","lemma":"צָפוֹן","morph":"여성 단수","pos":"명사","meanings":["북쪽"],"note":"전치사 מִן → ~로부터"}]},"여호수아 18:6":{"type":"wordblock","text":"וְ/אַתֶּ֞ם תִּכְתְּב֤וּ אֶת הָ/אָ֨רֶץ֙ שִׁבְעָ֣ה חֲלָקִ֔ים וַֽ/הֲבֵאתֶ֥ם אֵלַ֖/י הֵ֑נָּה וְ/יָרִ֨יתִי לָ/כֶ֤ם גּוֹרָל֙ פֹּ֔ה לִ/פְנֵ֖י יְהוָ֥ה אֱלֹהֵֽי/נוּ","words":[{"word":"וְ/אַתֶּ֞ם","pron":"브아템","meaning":"너","lemma":"אַתָּה","morph":"인칭 2인칭 남성 복수","pos":"대명사","meanings":["너"],"note":"접속사 וְ → 그리고"},{"word":"תִּכְתְּב֤וּ","pron":"틱트부","meaning":"쓰다","lemma":"כָּתַב","morph":"Qal 미완료 2인칭 남성 복수","pos":"동사","meanings":["쓰다","기록하다"]},{"word":"אֶת","pron":"엣","meaning":"(목적격)","lemma":"אֵת","morph":"직접목적격","pos":"소사","meanings":["직접 목적어 표지"]},{"word":"הָ/אָ֨רֶץ֙","pron":"하아렛","meaning":"땅","lemma":"אֶרֶץ","morph":"공성 단수","pos":"명사","meanings":["땅","토지","지역"],"note":"정관사 הַ → 그"},{"word":"שִׁבְעָ֣ה","pron":"십아","meaning":"일곱","lemma":"שֶׁבַע","morph":"기수 남성 단수","pos":"형용사","meanings":["일곱"]},{"word":"חֲלָקִ֔ים","pron":"하라킴","meaning":"분깃","lemma":"חֵלֶק","morph":"남성 복수","pos":"명사","meanings":["몫","분깃"]},{"word":"וַֽ/הֲבֵאתֶ֥ם","pron":"바하베템","meaning":"오다","lemma":"בּוֹא","morph":"Hiphil 연속완료 2인칭 남성 복수","pos":"동사","meanings":["오다","들어가다"],"note":"접속사 וְ → 그리고"},{"word":"אֵלַ֖/י","pron":"에라으","meaning":"~에게","lemma":"אֵל","morph":"","pos":"접미대명사","meanings":["~에게","~로"]},{"word":"הֵ֑נָּה","pron":"헤나","meaning":"여기","lemma":"הֵנָּה","morph":"","pos":"부사","meanings":["여기로","이리로"]},{"word":"וְ/יָרִ֨יתִי","pron":"브아리티","meaning":"가르치다","lemma":"יָרָה","morph":"Qal 연속완료 1인칭 공성 단수","pos":"동사","meanings":["가르치다","비를 내리다"],"note":"접속사 וְ → 그리고"},{"word":"לָ/כֶ֤ם","pron":"라켐","meaning":"~에게/를 위해","lemma":"l","morph":"","pos":"접미대명사","meanings":["~에게/를 위해"],"note":"전치사 לְ"},{"word":"גּוֹרָל֙","pron":"고랄","meaning":"제비","lemma":"גּוֹרָל","morph":"남성 단수","pos":"명사","meanings":["제비뽑기"]},{"word":"פֹּ֔ה","pron":"포","meaning":"여기","lemma":"פֹּה","morph":"","pos":"부사","meanings":["여기"]},{"word":"לִ/פְנֵ֖י","pron":"리프네","meaning":"얼굴","lemma":"פָּנִים","morph":"공성 복수","pos":"명사","meanings":["얼굴","앞"],"note":"전치사 לְ → ~에게/를 위해"},{"word":"יְהוָ֥ה","pron":"여호와","meaning":"여호와","lemma":"יְהֹוָה","morph":"고유","pos":"명사","meanings":["여호와"],"nameType":"person"},{"word":"אֱלֹהֵֽי/נוּ","pron":"에로헤누","meaning":"하나님","lemma":"אֱלֹהִים","morph":"남성 복수","pos":"명사","meanings":["하나님(엘로힘)","신들"]}]},"여호수아 18:7":{"type":"wordblock","text":"כִּ֠י אֵֽין חֵ֤לֶק לַ/לְוִיִּם֙ בְּ/קִרְבְּ/כֶ֔ם כִּֽי כְהֻנַּ֥ת יְהוָ֖ה נַחֲלָת֑/וֹ וְ/גָ֡ד וּ/רְאוּבֵ֡ן וַ/חֲצִי֩ שֵׁ֨בֶט הַֽ/מְנַשֶּׁ֜ה לָקְח֣וּ נַחֲלָתָ֗/ם מֵ/עֵ֤בֶר לַ/יַּרְדֵּן֙ מִזְרָ֔חָ/ה אֲשֶׁר֙ נָתַ֣ן לָ/הֶ֔ם מֹשֶׁ֖ה עֶ֥בֶד יְהוָֽה","words":[{"word":"כִּ֠י","pron":"키","meaning":"왜냐하면","lemma":"כִּי","morph":"","pos":"접속사","meanings":["~하기 때문에","참으로"]},{"word":"אֵֽין","pron":"엔","meaning":"없다","lemma":"אַיִן","morph":"부정","pos":"소사","meanings":["없다","아니다"]},{"word":"חֵ֤לֶק","pron":"헤렉","meaning":"분깃","lemma":"חֵלֶק","morph":"남성 단수","pos":"명사","meanings":["몫","분깃"]},{"word":"לַ/לְוִיִּם֙","pron":"라르비임","meaning":"레위인","lemma":"לֵוִיִּי","morph":"민족 남성 복수","pos":"명사","meanings":["레위 사람","레위인"],"note":"전치사 לְ → ~에게/를 위해"},{"word":"בְּ/קִרְבְּ/כֶ֔ם","pron":"브킬브켐","meaning":"속","lemma":"קֶרֶב","morph":"남성 단수","pos":"명사","meanings":["속","내부","중간"],"note":"전치사 בְּ → ~ 안에/으로"},{"word":"כִּֽי","pron":"키","meaning":"왜냐하면","lemma":"כִּי","morph":"","pos":"접속사","meanings":["~하기 때문에","참으로"]},{"word":"כְהֻנַּ֥ת","pron":"크후낫","meaning":"제사장직","lemma":"כְּהֻנָּה","morph":"여성 단수","pos":"명사","meanings":["제사장의 직무"]},{"word":"יְהוָ֖ה","pron":"여호와","meaning":"여호와","lemma":"יְהֹוָה","morph":"고유","pos":"명사","meanings":["여호와"],"nameType":"person"},{"word":"נַחֲלָת֑/וֹ","pron":"나하랏오","meaning":"기업","lemma":"נַחֲלָה","morph":"여성 단수","pos":"명사","meanings":["기업","유산","분깃"]},{"word":"וְ/גָ֡ד","pron":"브갇","meaning":"갓","lemma":"גָּד","morph":"고유","pos":"명사","meanings":["갓"],"nameType":"person","note":"접속사 וְ → 그리고"},{"word":"וּ/רְאוּבֵ֡ן","pron":"우르우벤","meaning":"르우벤","lemma":"רְאוּבֵן","morph":"고유","pos":"명사","meanings":["르우벤"],"nameType":"person","note":"접속사 וְ → 그리고"},{"word":"וַ/חֲצִי֩","pron":"바하찌","meaning":"절반","lemma":"חֵצִי","morph":"남성 단수","pos":"명사","meanings":["절반","중간"],"note":"접속사 וְ → 그리고"},{"word":"שֵׁ֨בֶט","pron":"세벧","meaning":"지팡이","lemma":"שֵׁבֶט","morph":"남성 단수","pos":"명사","meanings":["지팡이","지파"]},{"word":"הַֽ/מְנַשֶּׁ֜ה","pron":"하므나세","meaning":"므낫세","lemma":"מְנַשֶּׁה","morph":"고유","pos":"명사","meanings":["므낫세"],"nameType":"person","note":"정관사 הַ → 그"},{"word":"לָקְח֣וּ","pron":"락후","meaning":"잡다","lemma":"לָקַח","morph":"Qal 완료 3인칭 공성 복수","pos":"동사","meanings":["잡다","취하다"]},{"word":"נַחֲלָתָ֗/ם","pron":"나하라타므","meaning":"기업","lemma":"נַחֲלָה","morph":"여성 단수","pos":"명사","meanings":["기업","유산","분깃"]},{"word":"מֵ/עֵ֤בֶר","pron":"메에벨","meaning":"건너편","lemma":"עֵבֶר","morph":"남성 단수","pos":"명사","meanings":["건너편","맞은편"],"note":"전치사 מִן → ~로부터"},{"word":"לַ/יַּרְדֵּן֙","pron":"라알덴","meaning":"요단","lemma":"יַרְדֵּן","morph":"고유","pos":"명사","meanings":["요단"],"nameType":"place","note":"전치사 לְ → ~에게/를 위해"},{"word":"מִזְרָ֔חָ/ה","pron":"밋라하","meaning":"동","lemma":"מִזְרָח","morph":"남성 단수","pos":"명사","meanings":["해 뜨는 곳","동쪽"]},{"word":"אֲשֶׁר֙","pron":"아셀","meaning":"~한 것","lemma":"אֲשֶׁר","morph":"관계","pos":"소사","meanings":["~인","~한 것"]},{"word":"נָתַ֣ן","pron":"나탄","meaning":"주다","lemma":"נָתַן","morph":"Qal 완료 3인칭 남성 단수","pos":"동사","meanings":["주다","두다"]},{"word":"לָ/הֶ֔ם","pron":"라헴","meaning":"~에게/를 위해","lemma":"l","morph":"","pos":"접미대명사","meanings":["~에게/를 위해"],"note":"전치사 לְ"},{"word":"מֹשֶׁ֖ה","pron":"모세","meaning":"모세","lemma":"מֹשֶׁה","morph":"고유","pos":"명사","meanings":["모세"],"nameType":"person"},{"word":"עֶ֥בֶד","pron":"에벧","meaning":"종","lemma":"עֶבֶד","morph":"남성 단수","pos":"명사","meanings":["종","노예"]},{"word":"יְהוָֽה","pron":"여호와","meaning":"여호와","lemma":"יְהֹוָה","morph":"고유","pos":"명사","meanings":["여호와"],"nameType":"person"}]},"여호수아 18:8":{"type":"wordblock","text":"וַ/יָּקֻ֥מוּ הָ/אֲנָשִׁ֖ים וַ/יֵּלֵ֑כוּ וַ/יְצַ֣ו יְהוֹשֻׁ֡עַ אֶת הַ/הֹלְכִים֩ לִ/כְתֹּ֨ב אֶת הָ/אָ֜רֶץ לֵ/אמֹ֗ר לְ֠כוּ וְ/הִתְהַלְּכ֨וּ בָ/אָ֜רֶץ וְ/כִתְב֤וּ אוֹתָ/הּ֙ וְ/שׁ֣וּבוּ אֵלַ֔/י וּ֠/פֹה אַשְׁלִ֨יךְ לָ/כֶ֥ם גּוֹרָ֛ל לִ/פְנֵ֥י יְהוָ֖ה בְּ/שִׁלֹֽה","words":[{"word":"וַ/יָּקֻ֥מוּ","pron":"바아쿠무","meaning":"일어나다","lemma":"קוּם","morph":"Qal 연속미완료 3인칭 남성 복수","pos":"동사","meanings":["일어나다","세우다"],"note":"접속사 וְ → 그리고"},{"word":"הָ/אֲנָשִׁ֖ים","pron":"하아나심","meaning":"사람","lemma":"אִישׁ","morph":"남성 복수","pos":"명사","meanings":["사람","남자"],"note":"정관사 הַ → 그"},{"word":"וַ/יֵּלֵ֑כוּ","pron":"바에레쿠","meaning":"가다","lemma":"יָלַךְ","morph":"Qal 연속미완료 3인칭 남성 복수","pos":"동사","meanings":["가다","걷다","출발하다"],"note":"접속사 וְ → 그리고"},{"word":"וַ/יְצַ֣ו","pron":"바으짜브","meaning":"명령하다","lemma":"צָוָה","morph":"Piel 연속미완료 3인칭 남성 단수","pos":"동사","meanings":["명령하다","지시하다"],"note":"접속사 וְ → 그리고"},{"word":"יְהוֹשֻׁ֡עַ","pron":"으호수아","meaning":"여호수아","lemma":"יְהוֹשׁוּעַ","morph":"고유","pos":"명사","meanings":["여호수아"],"nameType":"person"},{"word":"אֶת","pron":"엣","meaning":"(목적격)","lemma":"אֵת","morph":"직접목적격","pos":"소사","meanings":["직접 목적어 표지"]},{"word":"הַ/הֹלְכִים֩","pron":"하홀킴","meaning":"가다","lemma":"הָלַךְ","morph":"Qal 분사 능동 남성 복수","pos":"동사","meanings":["가다","걷다"],"note":"정관사 הַ → 그"},{"word":"לִ/כְתֹּ֨ב","pron":"리크톱","meaning":"쓰다","lemma":"כָּתַב","morph":"Qal 부정사 연계","pos":"동사","meanings":["쓰다","기록하다"],"note":"전치사 לְ → ~에게/를 위해"},{"word":"אֶת","pron":"엣","meaning":"(목적격)","lemma":"אֵת","morph":"직접목적격","pos":"소사","meanings":["직접 목적어 표지"]},{"word":"הָ/אָ֜רֶץ","pron":"하아렛","meaning":"땅","lemma":"אֶרֶץ","morph":"공성 단수","pos":"명사","meanings":["땅","토지","지역"],"note":"정관사 הַ → 그"},{"word":"לֵ/אמֹ֗ר","pron":"레몰","meaning":"말하다","lemma":"אָמַר","morph":"Qal 부정사 연계","pos":"동사","meanings":["말하다","이르다"],"note":"전치사 לְ → ~에게/를 위해"},{"word":"לְ֠כוּ","pron":"르쿠","meaning":"가다","lemma":"יָלַךְ","morph":"Qal 권유형 2인칭 남성 복수","pos":"동사","meanings":["가다","걷다","출발하다"]},{"word":"וְ/הִתְהַלְּכ֨וּ","pron":"브힛할쿠","meaning":"가다","lemma":"הָלַךְ","morph":"Hithpael 권유형 2인칭 남성 복수","pos":"동사","meanings":["가다","걷다"],"note":"접속사 וְ → 그리고"},{"word":"בָ/אָ֜רֶץ","pron":"바아렛","meaning":"땅","lemma":"אֶרֶץ","morph":"공성 단수","pos":"명사","meanings":["땅","토지","지역"],"note":"전치사 בְּ → ~ 안에/으로"},{"word":"וְ/כִתְב֤וּ","pron":"브킷부","meaning":"쓰다","lemma":"כָּתַב","morph":"Qal 권유형 2인칭 남성 복수","pos":"동사","meanings":["쓰다","기록하다"],"note":"접속사 וְ → 그리고"},{"word":"אוֹתָ/הּ֙","pron":"오타흐","meaning":"(목적격)","lemma":"אֵת","morph":"","pos":"접미대명사","meanings":["직접 목적어 표지"]},{"word":"וְ/שׁ֣וּבוּ","pron":"브수부","meaning":"돌아오다","lemma":"שׁוּב","morph":"Qal 권유형 2인칭 남성 복수","pos":"동사","meanings":["돌아오다","되돌아가다"],"note":"접속사 וְ → 그리고"},{"word":"אֵלַ֔/י","pron":"에라으","meaning":"~에게","lemma":"אֵל","morph":"","pos":"접미대명사","meanings":["~에게","~로"]},{"word":"וּ֠/פֹה","pron":"우포","meaning":"여기","lemma":"פֹּה","morph":"","pos":"부사","meanings":["여기"],"note":"접속사 וְ → 그리고"},{"word":"אַשְׁלִ֨יךְ","pron":"앗릭","meaning":"던지다","lemma":"שָׁלַךְ","morph":"Hiphil 미완료 1인칭 공성 단수","pos":"동사","meanings":["내던지다","버리다"]},{"word":"לָ/כֶ֥ם","pron":"라켐","meaning":"~에게/를 위해","lemma":"l","morph":"","pos":"접미대명사","meanings":["~에게/를 위해"],"note":"전치사 לְ"},{"word":"גּוֹרָ֛ל","pron":"고랄","meaning":"제비","lemma":"גּוֹרָל","morph":"남성 단수","pos":"명사","meanings":["제비뽑기"]},{"word":"לִ/פְנֵ֥י","pron":"리프네","meaning":"얼굴","lemma":"פָּנִים","morph":"공성 복수","pos":"명사","meanings":["얼굴","앞"],"note":"전치사 לְ → ~에게/를 위해"},{"word":"יְהוָ֖ה","pron":"여호와","meaning":"여호와","lemma":"יְהֹוָה","morph":"고유","pos":"명사","meanings":["여호와"],"nameType":"person"},{"word":"בְּ/שִׁלֹֽה","pron":"브시로","meaning":"실로","lemma":"שִׁילֹה","morph":"고유","pos":"명사","meanings":["실로"],"nameType":"place","note":"전치사 בְּ → ~ 안에/으로"}]},"여호수아 18:9":{"type":"wordblock","text":"וַ/יֵּלְכ֤וּ הָֽ/אֲנָשִׁים֙ וַ/יַּעַבְר֣וּ בָ/אָ֔רֶץ וַ/יִּכְתְּב֧וּ/הָ לֶֽ/עָרִ֛ים לְ/שִׁבְעָ֥ה חֲלָקִ֖ים עַל סֵ֑פֶר וַ/יָּבֹ֧אוּ אֶל יְהוֹשֻׁ֛עַ אֶל הַֽ/מַּחֲנֶ֖ה שִׁלֹֽה","words":[{"word":"וַ/יֵּלְכ֤וּ","pron":"바엘쿠","meaning":"가다","lemma":"יָלַךְ","morph":"Qal 연속미완료 3인칭 남성 복수","pos":"동사","meanings":["가다","걷다","출발하다"],"note":"접속사 וְ → 그리고"},{"word":"הָֽ/אֲנָשִׁים֙","pron":"하아나심","meaning":"사람","lemma":"אִישׁ","morph":"남성 복수","pos":"명사","meanings":["사람","남자"],"note":"정관사 הַ → 그"},{"word":"וַ/יַּעַבְר֣וּ","pron":"바아압루","meaning":"건너다","lemma":"עָבַר","morph":"Qal 연속미완료 3인칭 남성 복수","pos":"동사","meanings":["건너가다","지나가다"],"note":"접속사 וְ → 그리고"},{"word":"בָ/אָ֔רֶץ","pron":"바아렛","meaning":"땅","lemma":"אֶרֶץ","morph":"공성 단수","pos":"명사","meanings":["땅","토지","지역"],"note":"전치사 בְּ → ~ 안에/으로"},{"word":"וַ/יִּכְתְּב֧וּ/הָ","pron":"바익트부하","meaning":"쓰다","lemma":"כָּתַב","morph":"Qal 연속미완료 3인칭 남성 복수","pos":"동사","meanings":["쓰다","기록하다"],"note":"접속사 וְ → 그리고"},{"word":"לֶֽ/עָרִ֛ים","pron":"레아림","meaning":"성읍","lemma":"עִיר","morph":"여성 복수","pos":"명사","meanings":["성","도시","성읍"],"note":"전치사 לְ → ~에게/를 위해"},{"word":"לְ/שִׁבְעָ֥ה","pron":"르십아","meaning":"일곱","lemma":"שֶׁבַע","morph":"","meanings":["일곱"],"note":"전치사 לְ → ~에게/를 위해"},{"word":"חֲלָקִ֖ים","pron":"하라킴","meaning":"분깃","lemma":"חֵלֶק","morph":"남성 복수","pos":"명사","meanings":["몫","분깃"]},{"word":"עַל","pron":"알","meaning":"~위에","lemma":"עַל","morph":"","pos":"전치사","meanings":["위에","관하여"]},{"word":"סֵ֑פֶר","pron":"세펠","meaning":"책","lemma":"סֵפֶר","morph":"남성 단수","pos":"명사","meanings":["책","문서"]},{"word":"וַ/יָּבֹ֧אוּ","pron":"바아보우","meaning":"오다","lemma":"בּוֹא","morph":"Qal 연속미완료 3인칭 남성 복수","pos":"동사","meanings":["오다","들어가다"],"note":"접속사 וְ → 그리고"},{"word":"אֶל","pron":"엘","meaning":"~에게","lemma":"אֵל","morph":"","pos":"전치사","meanings":["~에게","~로"]},{"word":"יְהוֹשֻׁ֛עַ","pron":"으호수아","meaning":"여호수아","lemma":"יְהוֹשׁוּעַ","morph":"고유","pos":"명사","meanings":["여호수아"],"nameType":"person"},{"word":"אֶל","pron":"엘","meaning":"~에게","lemma":"אֵל","morph":"","pos":"전치사","meanings":["~에게","~로"]},{"word":"הַֽ/מַּחֲנֶ֖ה","pron":"하마하네","meaning":"진영","lemma":"מַחֲנֶה","morph":"공성 단수","pos":"명사","meanings":["진","군대"],"note":"정관사 הַ → 그"},{"word":"שִׁלֹֽה","pron":"시로","meaning":"실로","lemma":"שִׁילֹה","morph":"고유","pos":"명사","meanings":["실로"],"nameType":"place"}]},"여호수아 18:10":{"type":"wordblock","text":"וַ/יַּשְׁלֵךְ֩ לָ/הֶ֨ם יְהוֹשֻׁ֧עַ גּוֹרָ֛ל בְּ/שִׁלֹ֖ה לִ/פְנֵ֣י יְהוָ֑ה וַ/יְחַלֶּק שָׁ֨ם יְהוֹשֻׁ֧עַ אֶת הָ/אָ֛רֶץ לִ/בְנֵ֥י יִשְׂרָאֵ֖ל כְּ/מַחְלְקֹתָֽ/ם","words":[{"word":"וַ/יַּשְׁלֵךְ֩","pron":"바앗렉","meaning":"던지다","lemma":"שָׁלַךְ","morph":"Hiphil 연속미완료 3인칭 남성 단수","pos":"동사","meanings":["내던지다","버리다"],"note":"접속사 וְ → 그리고"},{"word":"לָ/הֶ֨ם","pron":"라헴","meaning":"~에게/를 위해","lemma":"l","morph":"","pos":"접미대명사","meanings":["~에게/를 위해"],"note":"전치사 לְ"},{"word":"יְהוֹשֻׁ֧עַ","pron":"으호수아","meaning":"여호수아","lemma":"יְהוֹשׁוּעַ","morph":"고유","pos":"명사","meanings":["여호수아"],"nameType":"person"},{"word":"גּוֹרָ֛ל","pron":"고랄","meaning":"제비","lemma":"גּוֹרָל","morph":"남성 단수","pos":"명사","meanings":["제비뽑기"]},{"word":"בְּ/שִׁלֹ֖ה","pron":"브시로","meaning":"실로","lemma":"שִׁילֹה","morph":"고유","pos":"명사","meanings":["실로"],"nameType":"place","note":"전치사 בְּ → ~ 안에/으로"},{"word":"לִ/פְנֵ֣י","pron":"리프네","meaning":"얼굴","lemma":"פָּנִים","morph":"공성 복수","pos":"명사","meanings":["얼굴","앞"],"note":"전치사 לְ → ~에게/를 위해"},{"word":"יְהוָ֑ה","pron":"여호와","meaning":"여호와","lemma":"יְהֹוָה","morph":"고유","pos":"명사","meanings":["여호와"],"nameType":"person"},{"word":"וַ/יְחַלֶּק","pron":"바으하렉","meaning":"나누다","lemma":"חָלַק","morph":"Piel 연속미완료 3인칭 남성 단수","pos":"동사","meanings":["나누다","분배하다"],"note":"접속사 וְ → 그리고"},{"word":"שָׁ֨ם","pron":"삼","meaning":"거기에","lemma":"שָׁם","morph":"","pos":"부사","meanings":["거기에","그곳에"]},{"word":"יְהוֹשֻׁ֧עַ","pron":"으호수아","meaning":"여호수아","lemma":"יְהוֹשׁוּעַ","morph":"고유","pos":"명사","meanings":["여호수아"],"nameType":"person"},{"word":"אֶת","pron":"엣","meaning":"(목적격)","lemma":"אֵת","morph":"직접목적격","pos":"소사","meanings":["직접 목적어 표지"]},{"word":"הָ/אָ֛רֶץ","pron":"하아렛","meaning":"땅","lemma":"אֶרֶץ","morph":"공성 단수","pos":"명사","meanings":["땅","토지","지역"],"note":"정관사 הַ → 그"},{"word":"לִ/בְנֵ֥י","pron":"리브네","meaning":"아들","lemma":"בֵּן","morph":"남성 복수","pos":"명사","meanings":["아들","자손"],"note":"전치사 לְ → ~에게/를 위해"},{"word":"יִשְׂרָאֵ֖ל","pron":"이스라엘","meaning":"이스라엘","lemma":"יִשְׂרָאֵל","morph":"고유","pos":"명사","meanings":["이스라엘"],"nameType":"person"},{"word":"כְּ/מַחְלְקֹתָֽ/ם","pron":"크맣르코타므","meaning":"반열","lemma":"מַחֲלֹקֶת","morph":"여성 복수","pos":"명사","meanings":["부서","반"],"note":"전치사 כְּ → ~처럼"}]},"여호수아 18:11":{"type":"wordblock","text":"וַ/יַּ֗עַל גּוֹרַ֛ל מַטֵּ֥ה בְנֵֽי בִנְיָמִ֖ן לְ/מִשְׁפְּחֹתָ֑/ם וַ/יֵּצֵא֙ גְּב֣וּל גּֽוֹרָלָ֔/ם בֵּ֚ין בְּנֵ֣י יְהוּדָ֔ה וּ/בֵ֖ין בְּנֵ֥י יוֹסֵֽף","words":[{"word":"וַ/יַּ֗עַל","pron":"바아알","meaning":"올라가다","lemma":"עָלָה","morph":"Qal 연속미완료 3인칭 남성 단수","pos":"동사","meanings":["올라가다"],"note":"접속사 וְ → 그리고"},{"word":"גּוֹרַ֛ל","pron":"고랄","meaning":"제비","lemma":"גּוֹרָל","morph":"남성 단수","pos":"명사","meanings":["제비뽑기"]},{"word":"מַטֵּ֥ה","pron":"마데","meaning":"지팡이","lemma":"מַטֶּה","morph":"남성 단수","pos":"명사","meanings":["지팡이","지파","막대기"]},{"word":"בְנֵֽי","pron":"브네","meaning":"아들","lemma":"בֵּן","morph":"남성 복수","pos":"명사","meanings":["아들","자손"]},{"word":"בִנְיָמִ֖ן","pron":"빈아민","meaning":"베냐민","lemma":"בִּנְיָמִין","morph":"고유","pos":"명사","meanings":["베냐민"],"nameType":"person"},{"word":"לְ/מִשְׁפְּחֹתָ֑/ם","pron":"르밋프호타므","meaning":"가족","lemma":"מִשְׁפָּחָה","morph":"여성 복수","pos":"명사","meanings":["족속","가족","종족"],"note":"전치사 לְ → ~에게/를 위해"},{"word":"וַ/יֵּצֵא֙","pron":"바에쩨","meaning":"나가다","lemma":"יָצָא","morph":"Qal 연속미완료 3인칭 남성 단수","pos":"동사","meanings":["나가다","나오다"],"note":"접속사 וְ → 그리고"},{"word":"גְּב֣וּל","pron":"그불","meaning":"경계","lemma":"גְּבוּל","morph":"남성 단수","pos":"명사","meanings":["경계","지경"]},{"word":"גּֽוֹרָלָ֔/ם","pron":"고라라므","meaning":"제비","lemma":"גּוֹרָל","morph":"남성 단수","pos":"명사","meanings":["제비뽑기"]},{"word":"בֵּ֚ין","pron":"벤","meaning":"사이","lemma":"בֵּין","morph":"","pos":"전치사","meanings":["사이"]},{"word":"בְּנֵ֣י","pron":"브네","meaning":"아들","lemma":"בֵּן","morph":"남성 복수","pos":"명사","meanings":["아들","자손"]},{"word":"יְהוּדָ֔ה","pron":"으후다","meaning":"유다","lemma":"יְהוּדָה","morph":"고유","pos":"명사","meanings":["유다"],"nameType":"person"},{"word":"וּ/בֵ֖ין","pron":"우벤","meaning":"사이","lemma":"בֵּין","morph":"","pos":"전치사","meanings":["사이"],"note":"접속사 וְ → 그리고"},{"word":"בְּנֵ֥י","pron":"브네","meaning":"아들","lemma":"בֵּן","morph":"남성 복수","pos":"명사","meanings":["아들","자손"]},{"word":"יוֹסֵֽף","pron":"오셉","meaning":"요셉","lemma":"יוֹסֵף","morph":"고유","pos":"명사","meanings":["요셉"],"nameType":"person"}]},"여호수아 18:12":{"type":"wordblock","text":"וַ/יְהִ֨י לָ/הֶ֧ם הַ/גְּב֛וּל לִ/פְאַ֥ת צָפ֖וֹנָ/ה מִן הַ/יַּרְדֵּ֑ן וְ/עָלָ֣ה הַ/גְּבוּל֩ אֶל כֶּ֨תֶף יְרִיח֜וֹ מִ/צָּפ֗וֹן וְ/עָלָ֤ה בָ/הָר֙ יָ֔מָּ/ה ו/היה וְ/הָיוּ֙ תֹּֽצְאֹתָ֔י/ו מִדְבַּ֖רָ/ה בֵּ֥ית אָֽוֶן","words":[{"word":"וַ/יְהִ֨י","pron":"바으히","meaning":"되다","lemma":"הָיָה","morph":"Qal 연속미완료 3인칭 남성 단수","pos":"동사","meanings":["~이다","되다","있다"],"note":"접속사 וְ → 그리고"},{"word":"לָ/הֶ֧ם","pron":"라헴","meaning":"~에게/를 위해","lemma":"l","morph":"","pos":"접미대명사","meanings":["~에게/를 위해"],"note":"전치사 לְ"},{"word":"הַ/גְּב֛וּל","pron":"하그불","meaning":"경계","lemma":"גְּבוּל","morph":"남성 단수","pos":"명사","meanings":["경계","지경"],"note":"정관사 הַ → 그"},{"word":"לִ/פְאַ֥ת","pron":"리프앗","meaning":"모퉁이","lemma":"פֵּאָה","morph":"여성 단수","pos":"명사","meanings":["가장자리","모퉁이"],"note":"전치사 לְ → ~에게/를 위해"},{"word":"צָפ֖וֹנָ/ה","pron":"짜포나","meaning":"북쪽","lemma":"צָפוֹן","morph":"여성 단수","pos":"명사","meanings":["북쪽"]},{"word":"מִן","pron":"민","meaning":"~로부터","lemma":"מִן","morph":"","pos":"전치사","meanings":["~로부터","~중에서"]},{"word":"הַ/יַּרְדֵּ֑ן","pron":"하알덴","meaning":"요단","lemma":"יַרְדֵּן","morph":"고유","pos":"명사","meanings":["요단"],"nameType":"place","note":"정관사 הַ → 그"},{"word":"וְ/עָלָ֣ה","pron":"브아라","meaning":"올라가다","lemma":"עָלָה","morph":"Qal 연속완료 3인칭 남성 단수","pos":"동사","meanings":["올라가다"],"note":"접속사 וְ → 그리고"},{"word":"הַ/גְּבוּל֩","pron":"하그불","meaning":"경계","lemma":"גְּבוּל","morph":"남성 단수","pos":"명사","meanings":["경계","지경"],"note":"정관사 הַ → 그"},{"word":"אֶל","pron":"엘","meaning":"~에게","lemma":"אֵל","morph":"","pos":"전치사","meanings":["~에게","~로"]},{"word":"כֶּ֨תֶף","pron":"케텝","meaning":"어깨","lemma":"כָּתֵף","morph":"여성 단수","pos":"명사","meanings":["어깨","옆구리"]},{"word":"יְרִיח֜וֹ","pron":"으리호","meaning":"여리고","lemma":"יְרִיחוֹ","morph":"고유","pos":"명사","meanings":["여리고"],"nameType":"place"},{"word":"מִ/צָּפ֗וֹן","pron":"미짜폰","meaning":"북쪽","lemma":"צָפוֹן","morph":"여성 단수","pos":"명사","meanings":["북쪽"],"note":"전치사 מִן → ~로부터"},{"word":"וְ/עָלָ֤ה","pron":"브아라","meaning":"올라가다","lemma":"עָלָה","morph":"Qal 연속완료 3인칭 남성 단수","pos":"동사","meanings":["올라가다"],"note":"접속사 וְ → 그리고"},{"word":"בָ/הָר֙","pron":"바할","meaning":"산","lemma":"הַר","morph":"남성 단수","pos":"명사","meanings":["산"],"note":"전치사 בְּ → ~ 안에/으로"},{"word":"יָ֔מָּ/ה","pron":"아마","meaning":"바다","lemma":"יָם","morph":"남성 단수","pos":"명사","meanings":["바다"]},{"word":"ו/היה","pron":"브히","meaning":"되다","lemma":"הָיָה","morph":"Qal 연속완료 3인칭 남성 단수","pos":"동사","meanings":["~이다","되다","있다"],"note":"접속사 וְ → 그리고"},{"word":"וְ/הָיוּ֙","pron":"브하우","meaning":"되다","lemma":"הָיָה","morph":"Qal 연속완료 3인칭 공성 복수","pos":"동사","meanings":["~이다","되다","있다"],"note":"접속사 וְ → 그리고"},{"word":"תֹּֽצְאֹתָ֔י/ו","pron":"톳오타으브","meaning":"출입구","lemma":"תּוֹצָאָה","morph":"여성 복수","pos":"명사","meanings":["나가는 곳"]},{"word":"מִדְבַּ֖רָ/ה","pron":"믿바라","meaning":"광야","lemma":"מִדְבָּר","morph":"남성 단수","pos":"명사","meanings":["광야","들"]},{"word":"בֵּ֥ית","pron":"벳","meaning":"벧아웬","lemma":"בֵּית אָוֶן","morph":"고유","pos":"명사","meanings":["벧아웬"],"nameType":"place"},{"word":"אָֽוֶן","pron":"아벤","meaning":"벧아웬","lemma":"בֵּית אָוֶן","morph":"고유","pos":"명사","meanings":["벧아웬"],"nameType":"place"}]},"여호수아 18:13":{"type":"wordblock","text":"וְ/עָבַר֩ מִ/שָּׁ֨ם הַ/גְּב֜וּל ל֗וּזָ/ה אֶל כֶּ֤תֶף ל֨וּזָ/ה֙ נֶ֔גְבָּ/ה הִ֖יא בֵּֽית אֵ֑ל וְ/יָרַ֤ד הַ/גְּבוּל֙ עַטְר֣וֹת אַדָּ֔ר עַל הָ/הָ֕ר אֲשֶׁ֛ר מִ/נֶּ֥גֶב לְ/בֵית חֹר֖וֹן תַּחְתּֽוֹן","words":[{"word":"וְ/עָבַר֩","pron":"브아발","meaning":"건너다","lemma":"עָבַר","morph":"Qal 연속완료 3인칭 남성 단수","pos":"동사","meanings":["건너가다","지나가다"],"note":"접속사 וְ → 그리고"},{"word":"מִ/שָּׁ֨ם","pron":"미삼","meaning":"거기에","lemma":"שָׁם","morph":"","pos":"부사","meanings":["거기에","그곳에"],"note":"전치사 מִן → ~로부터"},{"word":"הַ/גְּב֜וּל","pron":"하그불","meaning":"경계","lemma":"גְּבוּל","morph":"남성 단수","pos":"명사","meanings":["경계","지경"],"note":"정관사 הַ → 그"},{"word":"ל֗וּזָ/ה","pron":"루자","meaning":"루스","lemma":"לוּז","morph":"고유","pos":"명사","meanings":["루스"],"nameType":"place"},{"word":"אֶל","pron":"엘","meaning":"~에게","lemma":"אֵל","morph":"","pos":"전치사","meanings":["~에게","~로"]},{"word":"כֶּ֤תֶף","pron":"케텝","meaning":"어깨","lemma":"כָּתֵף","morph":"여성 단수","pos":"명사","meanings":["어깨","옆구리"]},{"word":"ל֨וּזָ/ה֙","pron":"루자","meaning":"루스","lemma":"לוּז","morph":"고유","pos":"명사","meanings":["루스"],"nameType":"place"},{"word":"נֶ֔גְבָּ/ה","pron":"넥바","meaning":"남방","lemma":"נֶגֶב","morph":"남성 단수","pos":"명사","meanings":["남방","네게브"]},{"word":"הִ֖יא","pron":"히","meaning":"그","lemma":"הוּא","morph":"인칭 3인칭 여성 단수","pos":"대명사","meanings":["그","그것"]},{"word":"בֵּֽית","pron":"벳","meaning":"벧엘","lemma":"בֵּית־אֵל","morph":"고유","pos":"명사","meanings":["벧엘"],"nameType":"place"},{"word":"אֵ֑ל","pron":"엘","meaning":"벧엘","lemma":"בֵּית־אֵל","morph":"고유","pos":"명사","meanings":["벧엘"],"nameType":"place"},{"word":"וְ/יָרַ֤ד","pron":"브아랃","meaning":"내려가다","lemma":"יָרַד","morph":"Qal 연속완료 3인칭 남성 단수","pos":"동사","meanings":["내려가다"],"note":"접속사 וְ → 그리고"},{"word":"הַ/גְּבוּל֙","pron":"하그불","meaning":"경계","lemma":"גְּבוּל","morph":"남성 단수","pos":"명사","meanings":["경계","지경"],"note":"정관사 הַ → 그"},{"word":"עַטְר֣וֹת","pron":"앋롯","meaning":"아다롯앗달","lemma":"עַטְרוֹת אַדָּר","morph":"고유","pos":"명사","meanings":["아다롯앗달"],"nameType":"place"},{"word":"אַדָּ֔ר","pron":"아달","meaning":"아다롯앗달","lemma":"עַטְרוֹת אַדָּר","morph":"고유","pos":"명사","meanings":["아다롯앗달"],"nameType":"place"},{"word":"עַל","pron":"알","meaning":"~위에","lemma":"עַל","morph":"","pos":"전치사","meanings":["위에","관하여"]},{"word":"הָ/הָ֕ר","pron":"하할","meaning":"산","lemma":"הַר","morph":"남성 단수","pos":"명사","meanings":["산"],"note":"정관사 הַ → 그"},{"word":"אֲשֶׁ֛ר","pron":"아셀","meaning":"~한 것","lemma":"אֲשֶׁר","morph":"관계","pos":"소사","meanings":["~인","~한 것"]},{"word":"מִ/נֶּ֥גֶב","pron":"미네겝","meaning":"남방","lemma":"נֶגֶב","morph":"남성 단수","pos":"명사","meanings":["남방","네게브"],"note":"전치사 מִן → ~로부터"},{"word":"לְ/בֵית","pron":"르벳","meaning":"벧호론","lemma":"בֵּית חוֹרוֹן","morph":"고유","pos":"명사","meanings":["벧호론"],"nameType":"place","note":"전치사 לְ → ~에게/를 위해"},{"word":"חֹר֖וֹן","pron":"호론","meaning":"벧호론","lemma":"בֵּית חוֹרוֹן","morph":"고유","pos":"명사","meanings":["벧호론"],"nameType":"place"},{"word":"תַּחְתּֽוֹן","pron":"탛톤","meaning":"아래의","lemma":"תַּחְתּוֹן","morph":"남성 단수","pos":"형용사","meanings":["밑의"]}]},"여호수아 18:14":{"type":"wordblock","text":"וְ/תָאַ֣ר הַ/גְּבוּל֩ וְ/נָסַ֨ב לִ/פְאַת יָ֜ם נֶ֗גְבָּ/ה מִן הָ/הָר֙ אֲשֶׁ֨ר עַל פְּנֵ֥י בֵית חֹרוֹן֮ נֶגְבָּ/ה֒ ו/היה וְ/הָי֣וּ תֹֽצְאֹתָ֗י/ו אֶל קִרְיַת בַּ֨עַל֙ הִ֚יא קִרְיַ֣ת יְעָרִ֔ים עִ֖יר בְּנֵ֣י יְהוּדָ֑ה זֹ֖את פְּאַת יָֽם","words":[{"word":"וְ/תָאַ֣ר","pron":"브타알","meaning":"그리다","lemma":"תָּאַר","morph":"Qal 연속완료 3인칭 남성 단수","pos":"동사","meanings":["윤곽을 그리다"],"note":"접속사 וְ → 그리고"},{"word":"הַ/גְּבוּל֩","pron":"하그불","meaning":"경계","lemma":"גְּבוּל","morph":"남성 단수","pos":"명사","meanings":["경계","지경"],"note":"정관사 הַ → 그"},{"word":"וְ/נָסַ֨ב","pron":"브나삽","meaning":"두르다","lemma":"סָבַב","morph":"Niphal 연속완료 3인칭 남성 단수","pos":"동사","meanings":["두르다","돌다"],"note":"접속사 וְ → 그리고"},{"word":"לִ/פְאַת","pron":"리프앗","meaning":"모퉁이","lemma":"פֵּאָה","morph":"여성 단수","pos":"명사","meanings":["가장자리","모퉁이"],"note":"전치사 לְ → ~에게/를 위해"},{"word":"יָ֜ם","pron":"암","meaning":"바다","lemma":"יָם","morph":"남성 단수","pos":"명사","meanings":["바다"]},{"word":"נֶ֗גְבָּ/ה","pron":"넥바","meaning":"남방","lemma":"נֶגֶב","morph":"남성 단수","pos":"명사","meanings":["남방","네게브"]},{"word":"מִן","pron":"민","meaning":"~로부터","lemma":"מִן","morph":"","pos":"전치사","meanings":["~로부터","~중에서"]},{"word":"הָ/הָר֙","pron":"하할","meaning":"산","lemma":"הַר","morph":"남성 단수","pos":"명사","meanings":["산"],"note":"정관사 הַ → 그"},{"word":"אֲשֶׁ֨ר","pron":"아셀","meaning":"~한 것","lemma":"אֲשֶׁר","morph":"관계","pos":"소사","meanings":["~인","~한 것"]},{"word":"עַל","pron":"알","meaning":"~위에","lemma":"עַל","morph":"","pos":"전치사","meanings":["위에","관하여"]},{"word":"פְּנֵ֥י","pron":"프네","meaning":"얼굴","lemma":"פָּנִים","morph":"공성 복수","pos":"명사","meanings":["얼굴","앞"]},{"word":"בֵית","pron":"벳","meaning":"벧호론","lemma":"בֵּית חוֹרוֹן","morph":"고유","pos":"명사","meanings":["벧호론"],"nameType":"place"},{"word":"חֹרוֹן֮","pron":"호론","meaning":"벧호론","lemma":"בֵּית חוֹרוֹן","morph":"고유","pos":"명사","meanings":["벧호론"],"nameType":"place"},{"word":"נֶגְבָּ/ה֒","pron":"넥바","meaning":"남방","lemma":"נֶגֶב","morph":"남성 단수","pos":"명사","meanings":["남방","네게브"]},{"word":"ו/היה","pron":"브히","meaning":"되다","lemma":"הָיָה","morph":"Qal 연속완료 3인칭 남성 단수","pos":"동사","meanings":["~이다","되다","있다"],"note":"접속사 וְ → 그리고"},{"word":"וְ/הָי֣וּ","pron":"브하우","meaning":"되다","lemma":"הָיָה","morph":"Qal 연속완료 3인칭 공성 복수","pos":"동사","meanings":["~이다","되다","있다"],"note":"접속사 וְ → 그리고"},{"word":"תֹֽצְאֹתָ֗י/ו","pron":"톳오타으브","meaning":"출입구","lemma":"תּוֹצָאָה","morph":"여성 복수","pos":"명사","meanings":["나가는 곳"]},{"word":"אֶל","pron":"엘","meaning":"~에게","lemma":"אֵל","morph":"","pos":"전치사","meanings":["~에게","~로"]},{"word":"קִרְיַת","pron":"킬앗","meaning":"기럇바알","lemma":"קִרְיַת בַּעַל","morph":"고유","pos":"명사","meanings":["기럇바알"],"nameType":"place"},{"word":"בַּ֨עַל֙","pron":"바알","meaning":"기럇바알","lemma":"קִרְיַת בַּעַל","morph":"고유","pos":"명사","meanings":["기럇바알"],"nameType":"place"},{"word":"הִ֚יא","pron":"히","meaning":"그","lemma":"הוּא","morph":"인칭 3인칭 여성 단수","pos":"대명사","meanings":["그","그것"]},{"word":"קִרְיַ֣ת","pron":"킬앗","meaning":"기럇여아림","lemma":"קִרְיַת יְעָרִים","morph":"고유","pos":"명사","meanings":["기럇여아림"],"nameType":"place"},{"word":"יְעָרִ֔ים","pron":"으아림","meaning":"기럇여아림","lemma":"קִרְיַת יְעָרִים","morph":"고유","pos":"명사","meanings":["기럇여아림"],"nameType":"place"},{"word":"עִ֖יר","pron":"일","meaning":"성읍","lemma":"עִיר","morph":"여성 단수","pos":"명사","meanings":["성","도시","성읍"]},{"word":"בְּנֵ֣י","pron":"브네","meaning":"아들","lemma":"בֵּן","morph":"남성 복수","pos":"명사","meanings":["아들","자손"]},{"word":"יְהוּדָ֑ה","pron":"으후다","meaning":"유다","lemma":"יְהוּדָה","morph":"고유","pos":"명사","meanings":["유다"],"nameType":"person"},{"word":"זֹ֖את","pron":"좃","meaning":"이것","lemma":"זֹאת","morph":"지시 여성 단수","pos":"대명사","meanings":["이것(여성)"]},{"word":"פְּאַת","pron":"프앗","meaning":"모퉁이","lemma":"פֵּאָה","morph":"여성 단수","pos":"명사","meanings":["가장자리","모퉁이"]},{"word":"יָֽם","pron":"암","meaning":"바다","lemma":"יָם","morph":"남성 단수","pos":"명사","meanings":["바다"]}]},"여호수아 18:15":{"type":"wordblock","text":"וּ/פְאַת נֶ֕גְבָּ/ה מִ/קְצֵ֖ה קִרְיַ֣ת יְעָרִ֑ים וְ/יָצָ֤א הַ/גְּבוּל֙ יָ֔מָּ/ה וְ/יָצָ֕א אֶל מַעְיַ֖ן מֵ֥י נֶפְתּֽוֹחַ","words":[{"word":"וּ/פְאַת","pron":"우프앗","meaning":"모퉁이","lemma":"פֵּאָה","morph":"여성 단수","pos":"명사","meanings":["가장자리","모퉁이"],"note":"접속사 וְ → 그리고"},{"word":"נֶ֕גְבָּ/ה","pron":"넥바","meaning":"남방","lemma":"נֶגֶב","morph":"남성 단수","pos":"명사","meanings":["남방","네게브"]},{"word":"מִ/קְצֵ֖ה","pron":"미크쩨","meaning":"끝","lemma":"קָצֶה","morph":"공성 단수","pos":"명사","meanings":["끝","가장자리"],"note":"전치사 מִן → ~로부터"},{"word":"קִרְיַ֣ת","pron":"킬앗","meaning":"기럇여아림","lemma":"קִרְיַת יְעָרִים","morph":"고유","pos":"명사","meanings":["기럇여아림"],"nameType":"place"},{"word":"יְעָרִ֑ים","pron":"으아림","meaning":"기럇여아림","lemma":"קִרְיַת יְעָרִים","morph":"고유","pos":"명사","meanings":["기럇여아림"],"nameType":"place"},{"word":"וְ/יָצָ֤א","pron":"브아짜","meaning":"나가다","lemma":"יָצָא","morph":"Qal 연속완료 3인칭 남성 단수","pos":"동사","meanings":["나가다","나오다"],"note":"접속사 וְ → 그리고"},{"word":"הַ/גְּבוּל֙","pron":"하그불","meaning":"경계","lemma":"גְּבוּל","morph":"남성 단수","pos":"명사","meanings":["경계","지경"],"note":"정관사 הַ → 그"},{"word":"יָ֔מָּ/ה","pron":"아마","meaning":"바다","lemma":"יָם","morph":"남성 단수","pos":"명사","meanings":["바다"]},{"word":"וְ/יָצָ֕א","pron":"브아짜","meaning":"나가다","lemma":"יָצָא","morph":"Qal 연속완료 3인칭 남성 단수","pos":"동사","meanings":["나가다","나오다"],"note":"접속사 וְ → 그리고"},{"word":"אֶל","pron":"엘","meaning":"~에게","lemma":"אֵל","morph":"","pos":"전치사","meanings":["~에게","~로"]},{"word":"מַעְיַ֖ן","pron":"마으안","meaning":"샘","lemma":"מַעְיָן","morph":"남성 단수","pos":"명사","meanings":["샘"]},{"word":"מֵ֥י","pron":"메","meaning":"물","lemma":"מַיִם","morph":"남성 복수","pos":"명사","meanings":["물"]},{"word":"נֶפְתּֽוֹחַ","pron":"넵토하","meaning":"넵도아","lemma":"נֶפְתּוֹחַ","morph":"고유","pos":"명사","meanings":["넵도아"],"nameType":"place"}]},"여호수아 18:16":{"type":"wordblock","text":"וְ/יָרַ֨ד הַ/גְּב֜וּל אֶל קְצֵ֣ה הָ/הָ֗ר אֲשֶׁר֙ עַל פְּנֵי֙ גֵּ֣י בֶן הִנֹּ֔ם אֲשֶׁ֛ר בְּ/עֵ֥מֶק רְפָאִ֖ים צָפ֑וֹנָ/ה וְ/יָרַד֩ גֵּ֨י הִנֹּ֜ם אֶל כֶּ֤תֶף הַ/יְבוּסִי֙ נֶ֔גְבָּ/ה וְ/יָרַ֖ד עֵ֥ין רֹגֵֽל","words":[{"word":"וְ/יָרַ֨ד","pron":"브아랃","meaning":"내려가다","lemma":"יָרַד","morph":"Qal 연속완료 3인칭 남성 단수","pos":"동사","meanings":["내려가다"],"note":"접속사 וְ → 그리고"},{"word":"הַ/גְּב֜וּל","pron":"하그불","meaning":"경계","lemma":"גְּבוּל","morph":"남성 단수","pos":"명사","meanings":["경계","지경"],"note":"정관사 הַ → 그"},{"word":"אֶל","pron":"엘","meaning":"~에게","lemma":"אֵל","morph":"","pos":"전치사","meanings":["~에게","~로"]},{"word":"קְצֵ֣ה","pron":"크쩨","meaning":"끝","lemma":"קָצֶה","morph":"공성 단수","pos":"명사","meanings":["끝","가장자리"]},{"word":"הָ/הָ֗ר","pron":"하할","meaning":"산","lemma":"הַר","morph":"남성 단수","pos":"명사","meanings":["산"],"note":"정관사 הַ → 그"},{"word":"אֲשֶׁר֙","pron":"아셀","meaning":"~한 것","lemma":"אֲשֶׁר","morph":"관계","pos":"소사","meanings":["~인","~한 것"]},{"word":"עַל","pron":"알","meaning":"~위에","lemma":"עַל","morph":"","pos":"전치사","meanings":["위에","관하여"]},{"word":"פְּנֵי֙","pron":"프네","meaning":"얼굴","lemma":"פָּנִים","morph":"공성 복수","pos":"명사","meanings":["얼굴","앞"]},{"word":"גֵּ֣י","pron":"게","meaning":"골짜기","lemma":"גַּיְא","morph":"공성 단수","pos":"명사","meanings":["골짜기"]},{"word":"בֶן","pron":"벤","meaning":"아들","lemma":"בֵּן","morph":"남성 단수","pos":"명사","meanings":["아들","자손"]},{"word":"הִנֹּ֔ם","pron":"히놈","meaning":"힌놈","lemma":"הִנֹּם","morph":"고유","pos":"명사","meanings":["힌놈"],"nameType":"place"},{"word":"אֲשֶׁ֛ר","pron":"아셀","meaning":"~한 것","lemma":"אֲשֶׁר","morph":"관계","pos":"소사","meanings":["~인","~한 것"]},{"word":"בְּ/עֵ֥מֶק","pron":"브에멕","meaning":"골짜기","lemma":"עֵמֶק","morph":"남성 단수","pos":"명사","meanings":["골짜기"],"note":"전치사 בְּ → ~ 안에/으로"},{"word":"רְפָאִ֖ים","pron":"르파임","meaning":"거인","lemma":"רָפָא","morph":"고유","pos":"명사","meanings":["거인","르바임"]},{"word":"צָפ֑וֹנָ/ה","pron":"짜포나","meaning":"북쪽","lemma":"צָפוֹן","morph":"여성 단수","pos":"명사","meanings":["북쪽"]},{"word":"וְ/יָרַד֩","pron":"브아랃","meaning":"내려가다","lemma":"יָרַד","morph":"Qal 연속완료 3인칭 남성 단수","pos":"동사","meanings":["내려가다"],"note":"접속사 וְ → 그리고"},{"word":"גֵּ֨י","pron":"게","meaning":"골짜기","lemma":"גַּיְא","morph":"공성 단수","pos":"명사","meanings":["골짜기"]},{"word":"הִנֹּ֜ם","pron":"히놈","meaning":"힌놈","lemma":"הִנֹּם","morph":"고유","pos":"명사","meanings":["힌놈"],"nameType":"place"},{"word":"אֶל","pron":"엘","meaning":"~에게","lemma":"אֵל","morph":"","pos":"전치사","meanings":["~에게","~로"]},{"word":"כֶּ֤תֶף","pron":"케텝","meaning":"어깨","lemma":"כָּתֵף","morph":"여성 단수","pos":"명사","meanings":["어깨","옆구리"]},{"word":"הַ/יְבוּסִי֙","pron":"하으부시","meaning":"여부스 사람","lemma":"יְבוּסִי","morph":"민족 남성 단수","pos":"명사","meanings":["여부스 사람"],"nameType":"person","note":"민족 · 정관사 הַ → 그"},{"word":"נֶ֔גְבָּ/ה","pron":"넥바","meaning":"남방","lemma":"נֶגֶב","morph":"남성 단수","pos":"명사","meanings":["남방","네게브"]},{"word":"וְ/יָרַ֖ד","pron":"브아랃","meaning":"내려가다","lemma":"יָרַד","morph":"Qal 연속완료 3인칭 남성 단수","pos":"동사","meanings":["내려가다"],"note":"접속사 וְ → 그리고"},{"word":"עֵ֥ין","pron":"엔","meaning":"엔로겔","lemma":"עֵין רֹגֵל","morph":"고유","pos":"명사","meanings":["엔로겔"],"nameType":"place"},{"word":"רֹגֵֽל","pron":"로겔","meaning":"엔로겔","lemma":"עֵין רֹגֵל","morph":"고유","pos":"명사","meanings":["엔로겔"],"nameType":"place"}]},"여호수아 18:17":{"type":"wordblock","text":"וְ/תָאַ֣ר מִ/צָּפ֗וֹן וְ/יָצָא֙ עֵ֣ין שֶׁ֔מֶשׁ וְ/יָצָא֙ אֶל גְּלִיל֔וֹת אֲשֶׁר נֹ֖כַח מַעֲלֵ֣ה אֲדֻמִּ֑ים וְ/יָרַ֕ד אֶ֥בֶן בֹּ֖הַן בֶּן רְאוּבֵֽן","words":[{"word":"וְ/תָאַ֣ר","pron":"브타알","meaning":"그리다","lemma":"תָּאַר","morph":"Qal 연속완료 3인칭 남성 단수","pos":"동사","meanings":["윤곽을 그리다"],"note":"접속사 וְ → 그리고"},{"word":"מִ/צָּפ֗וֹן","pron":"미짜폰","meaning":"북쪽","lemma":"צָפוֹן","morph":"여성 단수","pos":"명사","meanings":["북쪽"],"note":"전치사 מִן → ~로부터"},{"word":"וְ/יָצָא֙","pron":"브아짜","meaning":"나가다","lemma":"יָצָא","morph":"Qal 연속완료 3인칭 남성 단수","pos":"동사","meanings":["나가다","나오다"],"note":"접속사 וְ → 그리고"},{"word":"עֵ֣ין","pron":"엔","meaning":"엔세메스","lemma":"עֵין שֶׁמֶשׁ","morph":"고유","pos":"명사","meanings":["엔세메스"],"nameType":"place"},{"word":"שֶׁ֔מֶשׁ","pron":"세멧","meaning":"엔세메스","lemma":"עֵין שֶׁמֶשׁ","morph":"고유","pos":"명사","meanings":["엔세메스"],"nameType":"place"},{"word":"וְ/יָצָא֙","pron":"브아짜","meaning":"나가다","lemma":"יָצָא","morph":"Qal 연속완료 3인칭 남성 단수","pos":"동사","meanings":["나가다","나오다"],"note":"접속사 וְ → 그리고"},{"word":"אֶל","pron":"엘","meaning":"~에게","lemma":"אֵל","morph":"","pos":"전치사","meanings":["~에게","~로"]},{"word":"גְּלִיל֔וֹת","pron":"그리롯","meaning":"그릴롯","lemma":"גְּלִילוֹת","morph":"고유","pos":"명사","meanings":["그릴롯"],"nameType":"place"},{"word":"אֲשֶׁר","pron":"아셀","meaning":"~한 것","lemma":"אֲשֶׁר","morph":"관계","pos":"소사","meanings":["~인","~한 것"]},{"word":"נֹ֖כַח","pron":"노캏","meaning":"앞에","lemma":"נֹכַח","morph":"","pos":"전치사","meanings":["맞은편","정면"]},{"word":"מַעֲלֵ֣ה","pron":"마아레","meaning":"오르막","lemma":"מַעֲלֶה","morph":"남성 단수","pos":"명사","meanings":["언덕길"]},{"word":"אֲדֻמִּ֑ים","pron":"아두밈","meaning":"아둠밈","lemma":"אֲדֻמִּים","morph":"고유","pos":"명사","meanings":["아둠밈"],"nameType":"place"},{"word":"וְ/יָרַ֕ד","pron":"브아랃","meaning":"내려가다","lemma":"יָרַד","morph":"Qal 연속완료 3인칭 남성 단수","pos":"동사","meanings":["내려가다"],"note":"접속사 וְ → 그리고"},{"word":"אֶ֥בֶן","pron":"에벤","meaning":"돌","lemma":"אֶבֶן","morph":"여성 단수","pos":"명사","meanings":["돌"]},{"word":"בֹּ֖הַן","pron":"보한","meaning":"보한","lemma":"בֹּהַן","morph":"고유","pos":"명사","meanings":["보한"],"nameType":"place"},{"word":"בֶּן","pron":"벤","meaning":"아들","lemma":"בֵּן","morph":"남성 단수","pos":"명사","meanings":["아들","자손"]},{"word":"רְאוּבֵֽן","pron":"르우벤","meaning":"르우벤","lemma":"רְאוּבֵן","morph":"고유","pos":"명사","meanings":["르우벤"],"nameType":"person"}]},"여호수아 18:18":{"type":"wordblock","text":"וְ/עָבַ֛ר אֶל כֶּ֥תֶף מוּל הָֽ/עֲרָבָ֖ה צָפ֑וֹנָ/ה וְ/יָרַ֖ד הָ/עֲרָבָֽתָ/ה","words":[{"word":"וְ/עָבַ֛ר","pron":"브아발","meaning":"건너다","lemma":"עָבַר","morph":"Qal 연속완료 3인칭 남성 단수","pos":"동사","meanings":["건너가다","지나가다"],"note":"접속사 וְ → 그리고"},{"word":"אֶל","pron":"엘","meaning":"~에게","lemma":"אֵל","morph":"","pos":"전치사","meanings":["~에게","~로"]},{"word":"כֶּ֥תֶף","pron":"케텝","meaning":"어깨","lemma":"כָּתֵף","morph":"여성 단수","pos":"명사","meanings":["어깨","옆구리"]},{"word":"מוּל","pron":"물","meaning":"맞은편","lemma":"מוּל","morph":"","pos":"전치사","meanings":["대면","앞"]},{"word":"הָֽ/עֲרָבָ֖ה","pron":"하아라바","meaning":"광야","lemma":"עֲרָבָה","morph":"여성 단수","pos":"명사","meanings":["사막","들"],"note":"정관사 הַ → 그"},{"word":"צָפ֑וֹנָ/ה","pron":"짜포나","meaning":"북쪽","lemma":"צָפוֹן","morph":"여성 단수","pos":"명사","meanings":["북쪽"]},{"word":"וְ/יָרַ֖ד","pron":"브아랃","meaning":"내려가다","lemma":"יָרַד","morph":"Qal 연속완료 3인칭 남성 단수","pos":"동사","meanings":["내려가다"],"note":"접속사 וְ → 그리고"},{"word":"הָ/עֲרָבָֽתָ/ה","pron":"하아라바타","meaning":"광야","lemma":"עֲרָבָה","morph":"여성 단수","pos":"명사","meanings":["사막","들"],"note":"정관사 הַ → 그"}]},"여호수아 18:19":{"type":"wordblock","text":"וְ/עָבַ֨ר הַ/גְּב֜וּל אֶל כֶּ֣תֶף בֵּית חָגְלָה֮ צָפוֹנָ/ה֒ ו/היה וְ/הָי֣וּ תצאותי/ו תֹּצְא֣וֹת הַ/גְּב֗וּל אֶל לְשׁ֤וֹן יָם הַ/מֶּ֨לַח֙ צָפ֔וֹנָ/ה אֶל קְצֵ֥ה הַ/יַּרְדֵּ֖ן נֶ֑גְבָּ/ה זֶ֖ה גְּב֥וּל נֶֽגֶב","words":[{"word":"וְ/עָבַ֨ר","pron":"브아발","meaning":"건너다","lemma":"עָבַר","morph":"Qal 연속완료 3인칭 남성 단수","pos":"동사","meanings":["건너가다","지나가다"],"note":"접속사 וְ → 그리고"},{"word":"הַ/גְּב֜וּל","pron":"하그불","meaning":"경계","lemma":"גְּבוּל","morph":"남성 단수","pos":"명사","meanings":["경계","지경"],"note":"정관사 הַ → 그"},{"word":"אֶל","pron":"엘","meaning":"~에게","lemma":"אֵל","morph":"","pos":"전치사","meanings":["~에게","~로"]},{"word":"כֶּ֣תֶף","pron":"케텝","meaning":"어깨","lemma":"כָּתֵף","morph":"여성 단수","pos":"명사","meanings":["어깨","옆구리"]},{"word":"בֵּית","pron":"벳","meaning":"벧호글라","lemma":"בֵּית חׇגְלָה","morph":"고유","pos":"명사","meanings":["벧호글라"],"nameType":"place"},{"word":"חָגְלָה֮","pron":"학라","meaning":"벧호글라","lemma":"בֵּית חׇגְלָה","morph":"고유","pos":"명사","meanings":["벧호글라"],"nameType":"place"},{"word":"צָפוֹנָ/ה֒","pron":"짜포나","meaning":"북쪽","lemma":"צָפוֹן","morph":"여성 단수","pos":"명사","meanings":["북쪽"]},{"word":"ו/היה","pron":"브히","meaning":"되다","lemma":"הָיָה","morph":"Qal 연속완료 3인칭 남성 단수","pos":"동사","meanings":["~이다","되다","있다"],"note":"접속사 וְ → 그리고"},{"word":"וְ/הָי֣וּ","pron":"브하우","meaning":"되다","lemma":"הָיָה","morph":"Qal 연속완료 3인칭 공성 복수","pos":"동사","meanings":["~이다","되다","있다"],"note":"접속사 וְ → 그리고"},{"word":"תצאותי/ו","pron":"틋브티브","meaning":"출입구","lemma":"תּוֹצָאָה","morph":"여성 복수","pos":"명사","meanings":["나가는 곳"]},{"word":"תֹּצְא֣וֹת","pron":"톳옷","meaning":"출입구","lemma":"תּוֹצָאָה","morph":"여성 복수","pos":"명사","meanings":["나가는 곳"]},{"word":"הַ/גְּב֗וּל","pron":"하그불","meaning":"경계","lemma":"גְּבוּל","morph":"남성 단수","pos":"명사","meanings":["경계","지경"],"note":"정관사 הַ → 그"},{"word":"אֶל","pron":"엘","meaning":"~에게","lemma":"אֵל","morph":"","pos":"전치사","meanings":["~에게","~로"]},{"word":"לְשׁ֤וֹן","pron":"르손","meaning":"혀","lemma":"לָשׁוֹן","morph":"공성 단수","pos":"명사","meanings":["혀","언어"]},{"word":"יָם","pron":"암","meaning":"바다","lemma":"יָם","morph":"남성 단수","pos":"명사","meanings":["바다"]},{"word":"הַ/מֶּ֨לַח֙","pron":"하메랗","meaning":"소금","lemma":"מֶלַח","morph":"남성 단수","pos":"명사","meanings":["소금"],"note":"정관사 הַ → 그"},{"word":"צָפ֔וֹנָ/ה","pron":"짜포나","meaning":"북쪽","lemma":"צָפוֹן","morph":"여성 단수","pos":"명사","meanings":["북쪽"]},{"word":"אֶל","pron":"엘","meaning":"~에게","lemma":"אֵל","morph":"","pos":"전치사","meanings":["~에게","~로"]},{"word":"קְצֵ֥ה","pron":"크쩨","meaning":"끝","lemma":"קָצֶה","morph":"공성 단수","pos":"명사","meanings":["끝","가장자리"]},{"word":"הַ/יַּרְדֵּ֖ן","pron":"하알덴","meaning":"요단","lemma":"יַרְדֵּן","morph":"고유","pos":"명사","meanings":["요단"],"nameType":"place","note":"정관사 הַ → 그"},{"word":"נֶ֑גְבָּ/ה","pron":"넥바","meaning":"남방","lemma":"נֶגֶב","morph":"남성 단수","pos":"명사","meanings":["남방","네게브"]},{"word":"זֶ֖ה","pron":"제","meaning":"이것","lemma":"זֶה","morph":"지시 남성 단수","pos":"대명사","meanings":["이것"]},{"word":"גְּב֥וּל","pron":"그불","meaning":"경계","lemma":"גְּבוּל","morph":"남성 단수","pos":"명사","meanings":["경계","지경"]},{"word":"נֶֽגֶב","pron":"네겝","meaning":"남방","lemma":"נֶגֶב","morph":"남성 단수","pos":"명사","meanings":["남방","네게브"]}]},"여호수아 18:20":{"type":"wordblock","text":"וְ/הַ/יַּרְדֵּ֥ן יִגְבֹּל אֹת֖/וֹ לִ/פְאַת קֵ֑דְמָ/ה זֹ֡את נַחֲלַת֩ בְּנֵ֨י בִנְיָמִ֧ן לִ/גְבֽוּלֹתֶ֛י/הָ סָבִ֖יב לְ/מִשְׁפְּחֹתָֽ/ם","words":[{"word":"וְ/הַ/יַּרְדֵּ֥ן","pron":"브하알덴","meaning":"요단","lemma":"יַרְדֵּן","morph":"고유","pos":"명사","meanings":["요단"],"nameType":"place","note":"접속사 וְ → 그리고 / 정관사 הַ → 그"},{"word":"יִגְבֹּל","pron":"익볼","meaning":"경계를 정하다","lemma":"גָּבַל","morph":"Qal 미완료 3인칭 남성 단수","pos":"동사","meanings":["한계를 두다"]},{"word":"אֹת֖/וֹ","pron":"옷오","meaning":"(목적격)","lemma":"אֵת","morph":"","pos":"접미대명사","meanings":["직접 목적어 표지"]},{"word":"לִ/פְאַת","pron":"리프앗","meaning":"모퉁이","lemma":"פֵּאָה","morph":"여성 단수","pos":"명사","meanings":["가장자리","모퉁이"],"note":"전치사 לְ → ~에게/를 위해"},{"word":"קֵ֑דְמָ/ה","pron":"켇마","meaning":"동방","lemma":"קֶדֶם","morph":"남성 단수","pos":"명사","meanings":["동방","옛","예전"]},{"word":"זֹ֡את","pron":"좃","meaning":"이것","lemma":"זֹאת","morph":"지시 여성 단수","pos":"대명사","meanings":["이것(여성)"]},{"word":"נַחֲלַת֩","pron":"나하랏","meaning":"기업","lemma":"נַחֲלָה","morph":"여성 단수","pos":"명사","meanings":["기업","유산","분깃"]},{"word":"בְּנֵ֨י","pron":"브네","meaning":"아들","lemma":"בֵּן","morph":"남성 복수","pos":"명사","meanings":["아들","자손"]},{"word":"בִנְיָמִ֧ן","pron":"빈아민","meaning":"베냐민","lemma":"בִּנְיָמִין","morph":"고유","pos":"명사","meanings":["베냐민"],"nameType":"person"},{"word":"לִ/גְבֽוּלֹתֶ֛י/הָ","pron":"리그부로테하","meaning":"경계","lemma":"גְּבוּלָה","morph":"여성 복수","pos":"명사","meanings":["국경"],"note":"전치사 לְ → ~에게/를 위해"},{"word":"סָבִ֖יב","pron":"사빕","meaning":"주위","lemma":"סָבִיב","morph":"공성 단수","pos":"명사","meanings":["주위","둘레"]},{"word":"לְ/מִשְׁפְּחֹתָֽ/ם","pron":"르밋프호타므","meaning":"가족","lemma":"מִשְׁפָּחָה","morph":"여성 복수","pos":"명사","meanings":["족속","가족","종족"],"note":"전치사 לְ → ~에게/를 위해"}]},"여호수아 18:21":{"type":"wordblock","text":"וְ/הָי֣וּ הֶֽ/עָרִ֗ים לְ/מַטֵּ֛ה בְּנֵ֥י בִנְיָמִ֖ן לְ/מִשְׁפְּחֽוֹתֵי/הֶ֑ם יְרִיח֥וֹ וּ/בֵית חָגְלָ֖ה וְ/עֵ֥מֶק קְצִֽיץ","words":[{"word":"וְ/הָי֣וּ","pron":"브하우","meaning":"되다","lemma":"הָיָה","morph":"Qal 완료 3인칭 공성 복수","pos":"동사","meanings":["~이다","되다","있다"],"note":"접속사 וְ → 그리고"},{"word":"הֶֽ/עָרִ֗ים","pron":"헤아림","meaning":"성읍","lemma":"עִיר","morph":"여성 복수","pos":"명사","meanings":["성","도시","성읍"],"note":"정관사 הַ → 그"},{"word":"לְ/מַטֵּ֛ה","pron":"르마데","meaning":"지팡이","lemma":"מַטֶּה","morph":"남성 단수","pos":"명사","meanings":["지팡이","지파","막대기"],"note":"전치사 לְ → ~에게/를 위해"},{"word":"בְּנֵ֥י","pron":"브네","meaning":"아들","lemma":"בֵּן","morph":"남성 복수","pos":"명사","meanings":["아들","자손"]},{"word":"בִנְיָמִ֖ן","pron":"빈아민","meaning":"베냐민","lemma":"בִּנְיָמִין","morph":"고유","pos":"명사","meanings":["베냐민"],"nameType":"person"},{"word":"לְ/מִשְׁפְּחֽוֹתֵי/הֶ֑ם","pron":"르밋프호테헴","meaning":"가족","lemma":"מִשְׁפָּחָה","morph":"여성 복수","pos":"명사","meanings":["족속","가족","종족"],"note":"전치사 לְ → ~에게/를 위해"},{"word":"יְרִיח֥וֹ","pron":"으리호","meaning":"여리고","lemma":"יְרִיחוֹ","morph":"고유","pos":"명사","meanings":["여리고"],"nameType":"place"},{"word":"וּ/בֵית","pron":"우벳","meaning":"벧호글라","lemma":"בֵּית חׇגְלָה","morph":"고유","pos":"명사","meanings":["벧호글라"],"nameType":"place","note":"접속사 וְ → 그리고"},{"word":"חָגְלָ֖ה","pron":"학라","meaning":"벧호글라","lemma":"בֵּית חׇגְלָה","morph":"고유","pos":"명사","meanings":["벧호글라"],"nameType":"place"},{"word":"וְ/עֵ֥מֶק","pron":"브에멕","meaning":"골짜기","lemma":"עֵמֶק","morph":"남성 단수","pos":"명사","meanings":["골짜기"],"note":"접속사 וְ → 그리고"},{"word":"קְצִֽיץ","pron":"크찟","meaning":"그시스","lemma":"קְצִיץ","morph":"고유","pos":"명사","meanings":["그시스"],"nameType":"place"}]},"여호수아 18:22":{"type":"wordblock","text":"וּ/בֵ֧ית הָֽעֲרָבָ֛ה וּ/צְמָרַ֖יִם וּ/בֵֽית אֵֽל","words":[{"word":"וּ/בֵ֧ית","pron":"우벳","meaning":"벧아라바","lemma":"בֵּית הָעֲרָבָה","morph":"고유","pos":"명사","meanings":["벧아라바"],"nameType":"place","note":"접속사 וְ → 그리고"},{"word":"הָֽעֲרָבָ֛ה","pron":"하아라바","meaning":"벧아라바","lemma":"בֵּית הָעֲרָבָה","morph":"고유","pos":"명사","meanings":["벧아라바"],"nameType":"place"},{"word":"וּ/צְמָרַ֖יִם","pron":"우쯔마라임","meaning":"스마라임","lemma":"צְמָרַיִם","morph":"고유","pos":"명사","meanings":["스마라임"],"nameType":"place","note":"접속사 וְ → 그리고"},{"word":"וּ/בֵֽית","pron":"우벳","meaning":"벧엘","lemma":"בֵּית־אֵל","morph":"고유","pos":"명사","meanings":["벧엘"],"nameType":"place","note":"접속사 וְ → 그리고"},{"word":"אֵֽל","pron":"엘","meaning":"벧엘","lemma":"בֵּית־אֵל","morph":"고유","pos":"명사","meanings":["벧엘"],"nameType":"place"}]},"여호수아 18:23":{"type":"wordblock","text":"וְ/הָ/עַוִּ֥ים וְ/הַ/פָּרָ֖ה וְ/עָפְרָֽה","words":[{"word":"וְ/הָ/עַוִּ֥ים","pron":"브하아빔","meaning":"아위 사람","lemma":"עַוִּים","morph":"고유","pos":"명사","meanings":["아위 사람"],"nameType":"person","note":"민족 · 접속사 וְ → 그리고 / 정관사 הַ → 그"},{"word":"וְ/הַ/פָּרָ֖ה","pron":"브하파라","meaning":"바라","lemma":"פָּרָה","morph":"고유","pos":"명사","meanings":["바라"],"nameType":"place","note":"접속사 וְ → 그리고 / 정관사 הַ → 그"},{"word":"וְ/עָפְרָֽה","pron":"브압라","meaning":"오브라","lemma":"עׇפְרָה","morph":"고유","pos":"명사","meanings":["오브라"],"nameType":"place","note":"접속사 וְ → 그리고"}]},"여호수아 18:24":{"type":"wordblock","text":"וּ/כְפַ֧ר העמני הָֽעַמֹּנָ֛ה וְ/הָֽ/עָפְנִ֖י וָ/גָ֑בַע עָרִ֥ים שְׁתֵּים עֶשְׂרֵ֖ה וְ/חַצְרֵי/הֶֽן","words":[{"word":"וּ/כְפַ֧ר","pron":"우크팔","meaning":"그발암모니","lemma":"כְּפַר הָעַמּוֹנִי","morph":"고유","pos":"명사","meanings":["그발암모니"],"nameType":"place","note":"접속사 וְ → 그리고"},{"word":"העמני","pron":"흠니","meaning":"그발암모니","lemma":"כְּפַר הָעַמּוֹנִי","morph":"고유","pos":"명사","meanings":["그발암모니"],"nameType":"place"},{"word":"הָֽעַמֹּנָ֛ה","pron":"하아모나","meaning":"그발암모니","lemma":"כְּפַר הָעַמּוֹנִי","morph":"고유","pos":"명사","meanings":["그발암모니"],"nameType":"place"},{"word":"וְ/הָֽ/עָפְנִ֖י","pron":"브하압니","meaning":"오브니 자손","lemma":"עׇפְנִי","morph":"고유","pos":"명사","meanings":["오브니 자손"],"nameType":"person","note":"민족 · 접속사 וְ → 그리고 / 정관사 הַ → 그"},{"word":"וָ/גָ֑בַע","pron":"바가바","meaning":"게바","lemma":"גֶּבַע","morph":"고유","pos":"명사","meanings":["게바"],"nameType":"place","note":"접속사 וְ → 그리고"},{"word":"עָרִ֥ים","pron":"아림","meaning":"성읍","lemma":"עִיר","morph":"여성 복수","pos":"명사","meanings":["성","도시","성읍"]},{"word":"שְׁתֵּים","pron":"스템","meaning":"둘","lemma":"שְׁנַיִם","morph":"기수 여성 양수","pos":"형용사","meanings":["둘"]},{"word":"עֶשְׂרֵ֖ה","pron":"엣레","meaning":"열","lemma":"עָשָׂר","morph":"기수 여성 단수","pos":"형용사","meanings":["열(자리수)"]},{"word":"וְ/חַצְרֵי/הֶֽן","pron":"브핫레헨","meaning":"뜰","lemma":"חָצֵר","morph":"공성 복수","pos":"명사","meanings":["뜰","마당"],"note":"접속사 וְ → 그리고"}]},"여호수아 18:25":{"type":"wordblock","text":"גִּבְע֥וֹן וְ/הָֽ/רָמָ֖ה וּ/בְאֵרֽוֹת","words":[{"word":"גִּבְע֥וֹן","pron":"깁온","meaning":"기브온","lemma":"גִּבְעוֹן","morph":"고유","pos":"명사","meanings":["기브온"],"nameType":"place"},{"word":"וְ/הָֽ/רָמָ֖ה","pron":"브하라마","meaning":"라마","lemma":"רָמָה","morph":"고유","pos":"명사","meanings":["라마"],"nameType":"place","note":"접속사 וְ → 그리고 / 정관사 הַ → 그"},{"word":"וּ/בְאֵרֽוֹת","pron":"우브에롯","meaning":"브에롯","lemma":"בְּאֵרוֹת","morph":"고유","pos":"명사","meanings":["브에롯"],"nameType":"place","note":"접속사 וְ → 그리고"}]},"여호수아 18:26":{"type":"wordblock","text":"וְ/הַ/מִּצְפֶּ֥ה וְ/הַ/כְּפִירָ֖ה וְ/הַ/מֹּצָֽה","words":[{"word":"וְ/הַ/מִּצְפֶּ֥ה","pron":"브하밋페","meaning":"미스베","lemma":"מִצְפֶּה","morph":"고유","pos":"명사","meanings":["미스베"],"nameType":"place","note":"접속사 וְ → 그리고 / 정관사 הַ → 그"},{"word":"וְ/הַ/כְּפִירָ֖ה","pron":"브하크피라","meaning":"그비라","lemma":"כְּפִירָה","morph":"고유","pos":"명사","meanings":["그비라"],"nameType":"place","note":"접속사 וְ → 그리고 / 정관사 הַ → 그"},{"word":"וְ/הַ/מֹּצָֽה","pron":"브하모짜","meaning":"모사","lemma":"מֹצָה","morph":"고유","pos":"명사","meanings":["모사"],"nameType":"place","note":"접속사 וְ → 그리고 / 정관사 הַ → 그"}]},"여호수아 18:27":{"type":"wordblock","text":"וְ/רֶ֥קֶם וְ/יִרְפְּאֵ֖ל וְ/תַרְאֲלָֽה","words":[{"word":"וְ/רֶ֥קֶם","pron":"브레켐","meaning":"레겜","lemma":"רֶקֶם","morph":"고유","pos":"명사","meanings":["레겜"],"nameType":"place","note":"접속사 וְ → 그리고"},{"word":"וְ/יִרְפְּאֵ֖ל","pron":"브일프엘","meaning":"이르브엘","lemma":"יִרְפְּאֵל","morph":"고유","pos":"명사","meanings":["이르브엘"],"nameType":"person","note":"접속사 וְ → 그리고"},{"word":"וְ/תַרְאֲלָֽה","pron":"브탈아라","meaning":"다라랏","lemma":"תַּרְאֲלָה","morph":"고유","pos":"명사","meanings":["다라랏"],"nameType":"place","note":"접속사 וְ → 그리고"}]},"여호수아 18:28":{"type":"wordblock","text":"וְ/צֵלַ֡ע הָאֶ֜לֶף וְ/הַ/יְבוּסִ֨י הִ֤יא יְרֽוּשָׁלִַ֨ם֙ גִּבְעַ֣ת קִרְיַ֔ת עָרִ֥ים אַרְבַּֽע עֶשְׂרֵ֖ה וְ/חַצְרֵי/הֶ֑ן זֹ֛את נַֽחֲלַ֥ת בְּנֵֽי בִנְיָמִ֖ן לְ/מִשְׁפְּחֹתָֽ/ם","words":[{"word":"וְ/צֵלַ֡ע","pron":"브쩨라","meaning":"셀라","lemma":"צֶלַע","morph":"고유","pos":"명사","meanings":["셀라"],"nameType":"place","note":"접속사 וְ → 그리고"},{"word":"הָאֶ֜לֶף","pron":"하에렙","meaning":"엘렙","lemma":"אֶלֶף","morph":"고유","pos":"명사","meanings":["엘렙"],"nameType":"place"},{"word":"וְ/הַ/יְבוּסִ֨י","pron":"브하으부시","meaning":"여부스 사람","lemma":"יְבוּסִי","morph":"민족 남성 단수","pos":"명사","meanings":["여부스 사람"],"nameType":"person","note":"민족 · 접속사 וְ → 그리고 / 정관사 הַ → 그"},{"word":"הִ֤יא","pron":"히","meaning":"그","lemma":"הוּא","morph":"인칭 3인칭 여성 단수","pos":"대명사","meanings":["그","그것"]},{"word":"יְרֽוּשָׁלִַ֨ם֙","pron":"예루살렘","meaning":"예루살렘","lemma":"יְרוּשָׁלִַ͏ם","morph":"고유","pos":"명사","meanings":["예루살렘"],"nameType":"place"},{"word":"גִּבְעַ֣ת","pron":"깁앗","meaning":"기부앗","lemma":"גִּבְעַת","morph":"고유","pos":"명사","meanings":["기부앗"],"nameType":"place"},{"word":"קִרְיַ֔ת","pron":"킬앗","meaning":"기럇여아림","lemma":"קִרְיַת יְעָרִים","morph":"고유","pos":"명사","meanings":["기럇여아림"],"nameType":"place"},{"word":"עָרִ֥ים","pron":"아림","meaning":"성읍","lemma":"עִיר","morph":"여성 복수","pos":"명사","meanings":["성","도시","성읍"]},{"word":"אַרְבַּֽע","pron":"알바","meaning":"넷","lemma":"אַרְבַּע","morph":"기수 여성 단수","pos":"형용사","meanings":["넷"]},{"word":"עֶשְׂרֵ֖ה","pron":"엣레","meaning":"열","lemma":"עָשָׂר","morph":"기수 여성 단수","pos":"형용사","meanings":["열(자리수)"]},{"word":"וְ/חַצְרֵי/הֶ֑ן","pron":"브핫레헨","meaning":"뜰","lemma":"חָצֵר","morph":"공성 복수","pos":"명사","meanings":["뜰","마당"],"note":"접속사 וְ → 그리고"},{"word":"זֹ֛את","pron":"좃","meaning":"이것","lemma":"זֹאת","morph":"지시 여성 단수","pos":"대명사","meanings":["이것(여성)"]},{"word":"נַֽחֲלַ֥ת","pron":"나하랏","meaning":"기업","lemma":"נַחֲלָה","morph":"여성 단수","pos":"명사","meanings":["기업","유산","분깃"]},{"word":"בְּנֵֽי","pron":"브네","meaning":"아들","lemma":"בֵּן","morph":"남성 복수","pos":"명사","meanings":["아들","자손"]},{"word":"בִנְיָמִ֖ן","pron":"빈아민","meaning":"베냐민","lemma":"בִּנְיָמִין","morph":"고유","pos":"명사","meanings":["베냐민"],"nameType":"person"},{"word":"לְ/מִשְׁפְּחֹתָֽ/ם","pron":"르밋프호타므","meaning":"가족","lemma":"מִשְׁפָּחָה","morph":"여성 복수","pos":"명사","meanings":["족속","가족","종족"],"note":"전치사 לְ → ~에게/를 위해"}]}}}
