{"chapter":15,"layer":"kids","verses":{"민수기 15:1":{"type":"text","content":"여호와께서 모세에게 말씀하셨어요."},"민수기 15:2":{"type":"text","content":"\"이스라엘 자손에게 알려서 말해라. '너희가 내가 너희에게 주어 거하게 할 땅에 들어가서,"},"민수기 15:3":{"type":"text","content":"여호와께 화제(불로 태워 드리는 제물)나 번제나 서원을 갚는 제사나 자원하여 드리는 제사나 정한 절기 제사로 소나 양으로 여호와께 향기롭게 드릴 때에는,"},"민수기 15:4":{"type":"text","content":"그 예물을 드리는 자는 고운 가루 에바의 10분의 1에 기름 한 힌의 4분의 1을 섞어 여호와께 소제로 드려야 한다."},"민수기 15:5":{"type":"text","content":"번제나 다른 제사로 드리는 제물이 어린 양이면, 전제(부어 드리는 술 제물)로 포도주 한 힌의 4분의 1을 준비해야 한다."},"민수기 15:6":{"type":"text","content":"숫양이면 소제로 고운 가루 한 에바의 10분의 2에 기름 한 힌의 3분의 1을 섞어 준비하고,"},"민수기 15:7":{"type":"text","content":"전제로 포도주 한 힌의 3분의 1을 드려 여호와 앞에 향기롭게 해야 한다."},"민수기 15:8":{"type":"text","content":"번제나 서원을 갚는 제사나 화목제로 수송아지를 준비하여 여호와께 드릴 때에는,"},"민수기 15:9":{"type":"text","content":"소제로 고운 가루 한 에바의 10분의 3에 기름 반 힌을 섞어 그 수송아지와 함께 드리고,"},"민수기 15:10":{"type":"text","content":"전제로 포도주 반 힌을 드려 여호와 앞에 향기로운 화제를 삼아야 한다."},"민수기 15:11":{"type":"text","content":"수송아지나 숫양이나 어린 숫양이나 어린 염소에 대해서는 그 마리 수마다 위와 같이 행하되,"},"민수기 15:12":{"type":"text","content":"너희가 준비하는 수에 따라 각기 수에 맞게 해야 한다."},"민수기 15:13":{"type":"text","content":"무릇 본토에서 태어난 자가 여호와께 향기로운 화제를 드릴 때에는 이 법대로 해야 한다."},"민수기 15:14":{"type":"text","content":"너희 중에 머무는 외국인이나, 너희 중에 대대로 있는 자가 누구든지 여호와께 향기로운 화제를 드릴 때에는, 너희가 하는 대로 그도 그렇게 해야 한다."},"민수기 15:15":{"type":"text","content":"회중, 곧 너희와 너희 중에 머무는 외국인이 한 규례를 따라야 하니, 너희 대대로의 영원한 규례이다. 너희가 어떠한 대로 외국인도 여호와 앞에 그러하리라."},"민수기 15:16":{"type":"text","content":"너희나 너희 중에 머무는 외국인이나 한 법도, 한 규례를 따라야 한다.'\""},"민수기 15:17":{"type":"text","content":"여호와께서 모세에게 말씀하셨어요."},"민수기 15:18":{"type":"text","content":"\"이스라엘 자손에게 알려서 말해라. '너희가 내가 인도하는 땅에 들어가거든,"},"민수기 15:19":{"type":"text","content":"그 땅의 양식을 먹을 때에 여호와께 거제(들어 올려 드리는 제물)를 드려야 한다."},"민수기 15:20":{"type":"text","content":"너희의 처음 익은 곡식 가루로 떡을 만들어 거제로 드리되, 타작 마당에서 드리는 거제처럼 들어 드려야 한다."},"민수기 15:21":{"type":"text","content":"너희의 처음 익은 곡식 가루 떡을 대대로 여호와께 거제로 드려야 한다.'\""},"민수기 15:22":{"type":"text","content":"\"너희가 모르고 죄를 범하여 여호와가 모세에게 말한 이 모든 명령을 지키지 못하되,"},"민수기 15:23":{"type":"text","content":"곧 여호와가 모세를 통해 너희에게 명한 모든 것을, 여호와가 명한 날부터 그 후 너희 대대로 지키지 못하여,"},"민수기 15:24":{"type":"text","content":"회중이 모르는 중에 잘못 죄를 범하였거든, 온 회중은 수송아지 한 마리를 여호와께 향기로운 화제로 드리고, 규례대로 그 소제와 전제를 드리고, 수염소 한 마리를 속죄제로 드려야 한다."},"민수기 15:25":{"type":"text","content":"제사장이 이스라엘 자손의 온 회중을 위해 속죄하면 그들이 용서를 받을 것이다. 이는 모르고 범한 죄이며, 또 그 모르고 범한 죄로 인해 예물, 곧 화제와 속죄제를 여호와께 드렸기 때문이다."},"민수기 15:26":{"type":"text","content":"이스라엘 자손의 온 회중과 그들 중에 머무는 외국인도 용서를 받을 것이니, 이는 온 백성이 모르고 죄를 범하였기 때문이다."},"민수기 15:27":{"type":"text","content":"만일 한 사람이 모르고 죄를 범하거든, 일 년 된 암염소로 속죄제를 드려야 한다."},"민수기 15:28":{"type":"text","content":"제사장은 그 모르고 범죄한 사람이 잘못하여 여호와 앞에 얻은 죄를 위해 속죄하여 그 죄를 속하면, 그가 용서를 받을 것이다."},"민수기 15:29":{"type":"text","content":"이스라엘 자손 중 본토에서 태어난 자나, 그들 중에 머무는 외국인이나, 무릇 모르고 죄를 범한 자에게 대한 법은 동일하다."},"민수기 15:30":{"type":"text","content":"그러나 본토에서 태어난 자든 외국인이든, 무릇 일부러 무엇을 행하면 여호와를 모독하는 자이니, 그는 자기 백성 중에서 끊어질 것이다."},"민수기 15:31":{"type":"text","content":"그런 사람은 여호와의 말씀을 멸시하고 그 명령을 파괴하였으니, 그 죄악이 자기에게 돌아가 온전히 끊어질 것이다.\""},"민수기 15:32":{"type":"text","content":"이스라엘 자손이 광야에 거할 때, 안식일에 어떤 사람이 나무하는 것이 발견되었어요."},"민수기 15:33":{"type":"text","content":"그 나무하는 자를 발견한 자들이 그를 모세와 아론과 온 회중 앞으로 끌고 왔는데,"},"민수기 15:34":{"type":"text","content":"어떻게 처리해야 할지 지시받지 못했으므로 그를 가두어 두었어요."},"민수기 15:35":{"type":"text","content":"여호와께서 모세에게 말씀하셨어요. \"그 사람을 반드시 죽여라. 온 회중이 진영 밖에서 돌로 그를 쳐 죽여라.\""},"민수기 15:36":{"type":"text","content":"온 회중이 곧 그를 진영 밖으로 끌어내어 돌로 그를 쳐 죽였으니, 여호와께서 모세에게 명령하신 대로였어요."},"민수기 15:37":{"type":"text","content":"여호와께서 모세에게 말씀하셨어요."},"민수기 15:38":{"type":"text","content":"\"이스라엘 자손에게 명령하여, 그들의 대대로 그 옷단 귀퉁이에 술(장식 끈)을 만들고, 청색 끈을 그 귀퉁이의 술에 더하게 해라."},"민수기 15:39":{"type":"text","content":"이 술은 너희가 보고 여호와의 모든 계명을 기억하여 지켜 행하고, 너희가 방탕에 빠뜨리는 자기 마음과 눈의 욕심을 따라가지 않게 하기 위함이다."},"민수기 15:40":{"type":"text","content":"그리하면 너희가 나의 모든 계명을 기억하고 지켜 행하여, 너희 하나님 앞에 거룩하게 될 것이다."},"민수기 15:41":{"type":"text","content":"나는 너희의 하나님이 되려고 너희를 애굽 땅에서 인도하여 낸 여호와 너희 하나님이다. 나는 여호와 너희 하나님이다.\""}}}
